Workbook

Sheet README
A1: Third-Party & Vendor Risk Management Program Workbook
A2: Vendor assessment package for an organization using cloud providers and AI software vendors. Sample organization: Meridian Analytics Group (fictional); all vendors and data are fictional.
A4: Purpose | B4: Provides a complete, reusable vendor risk assessment package: questionnaire, inherent and residual risk scoring, due diligence checklist, vendor risk register, approval workflow and monitoring schedule. Aligned to ISO/IEC 27001:2022 (Annex A.5.19–A.5.23), ISO/IEC 42001:2023, NIST CSF 2.0 (GV.SC) and NIST AI RMF.
A5: How to use | B5: 1. Review and adjust scoring parameters in Methodology (weights, thresholds, cadence) to match your risk appetite. 2. Add each vendor in Vendor_Register and score the six inherent risk factors (1–5). 3. Send the Questionnaire; record the vendor's answers in that vendor's column. 4. Work through Due_Diligence for the vendor (select the Vendor ID in cell B3). 5. Review Assessment_Results and the recommended decision in Vendor_Register. 6. Log individual risks and treatment plans in Risk_Register. 7. Obtain approval per Approval_Workflow and set the review dates in Monitoring.
A6: Colour legend | B6: Blue text on a pale yellow fill = input cell you may edit. Black text = formula (do not overwrite). Rating colours: green = Low, yellow = Medium, orange = High, dark red = Critical.
A7: Sheets | B7: Dashboard – portfolio summary and heat map Vendor_Register – inventory, inherent and residual scoring, decision, review dates Methodology – all weights, thresholds and assumptions Questionnaire – 51 weighted control questions (incl. 8 AI-specific), 7 critical controls Assessment_Results – control effectiveness by vendor and domain Due_Diligence – 34-item checklist (general, cloud and AI) Risk_Register – 5×5 scored vendor risks with treatment Approval_Workflow – 10-stage workflow, authority matrix, exception rules Monitoring – cadence by tier, calculated review calendar, triggers
A8: Sample data | B8: Six fictional vendors (two cloud infrastructure/backup, one SaaS CRM, one survey tool, two AI platforms) demonstrate every rating band, a critical control gap, an overdue reassessment and an expired attestation. Delete or overwrite them before real use. Capacity: 10 vendors in the register and questionnaire, 30 risks in Risk_Register.
A9: Assumptions & limits | B9: Weights, thresholds, the 70% maximum risk reduction and the impact scale are illustrative defaults, not regulatory requirements; calibrate them to the organization. Standard control mappings are indicative and should be validated against the published standards. The assessment as-of date is set in Methodology!B4 (use =TODAY() for live tracking).
A10: Confidentiality | B10: Never store real vendor questionnaires, contracts, credentials or client data in a public repository.
A11: Version | B11: v1.0 | Created October 2026 | Author: Saad Ali

Sheet Dashboard
A1: Third-Party Risk Dashboard
A2: Sample organization: Meridian Analytics Group (fictional). All figures calculate from the other sheets.
A3: Key indicators
A4: Vendors in register | B4: =SUMPRODUCT(--(Vendor_Register!A6:A15<>"")) -> 6
A5: Average inherent risk score | B5: =IFERROR(AVERAGE(Vendor_Register!L6:L15),"") -> 63
A6: Average control effectiveness | B6: =IFERROR(AVERAGE(Vendor_Register!N6:N15),"") -> 0.76250701
A7: Vendors with critical control gaps | B7: =COUNTIF(Vendor_Register!O6:O15,">0") -> 1
A8: Reassessments overdue | B8: =COUNTIF(Vendor_Register!X6:X15,"Overdue") -> 1
A9: Open vendor risks (open or in progress) | B9: =COUNTIF(Risk_Register!S6:S35,"Open")+COUNTIF(Risk_Register!S6:S35,"In Progress") -> 10
A10: High or Critical residual risks (open items) | B10: =SUMPRODUCT(((Risk_Register!N6:N35="High")+(Risk_Register!N6:N35="Critical"))*((Risk_Register!S6:S35="Open")+(Risk_Register!S6:S35="In Progress"))) -> 1
A12: Risk rating distribution (vendors)
A13: Rating | B13: Inherent | C13: Residual
A14: Low | B14: =COUNTIF(Vendor_Register!M6:M15,A14) -> 1 | C14: =COUNTIF(Vendor_Register!Q6:Q15,A14) -> 3
A15: Medium | B15: =COUNTIF(Vendor_Register!M6:M15,A15) -> 1 | C15: =COUNTIF(Vendor_Register!Q6:Q15,A15) -> 2
A16: High | B16: =COUNTIF(Vendor_Register!M6:M15,A16) -> 3 | C16: =COUNTIF(Vendor_Register!Q6:Q15,A16) -> 1
A17: Critical | B17: =COUNTIF(Vendor_Register!M6:M15,A17) -> 1 | C17: =COUNTIF(Vendor_Register!Q6:Q15,A17) -> 0
A19: Approval status
A20: Status | B20: Vendors
A21: Prospective | B21: =COUNTIF(Vendor_Register!T6:T15,A21) -> 0
A22: Under Review | B22: =COUNTIF(Vendor_Register!T6:T15,A22) -> 1
A23: Approved | B23: =COUNTIF(Vendor_Register!T6:T15,A23) -> 4
A24: Conditionally Approved | B24: =COUNTIF(Vendor_Register!T6:T15,A24) -> 1
A25: Rejected | B25: =COUNTIF(Vendor_Register!T6:T15,A25) -> 0
A26: Offboarded | B26: =COUNTIF(Vendor_Register!T6:T15,A26) -> 0
A28: Residual risk heat map (Risk_Register: count of risks)
A29: Impact ↓ / Likelihood → | B29: 1 | C29: 2 | D29: 3 | E29: 4 | F29: 5
A30: 5 | B30: =COUNTIFS(Risk_Register!$K$6:$K$35,1,Risk_Register!$L$6:$L$35,5,Risk_Register!$S$6:$S$35,"<>Closed") -> 0 | C30: =COUNTIFS(Risk_Register!$K$6:$K$35,2,Risk_Register!$L$6:$L$35,5,Risk_Register!$S$6:$S$35,"<>Closed") -> 1 | D30: =COUNTIFS(Risk_Register!$K$6:$K$35,3,Risk_Register!$L$6:$L$35,5,Risk_Register!$S$6:$S$35,"<>Closed") -> 0 | E30: =COUNTIFS(Risk_Register!$K$6:$K$35,4,Risk_Register!$L$6:$L$35,5,Risk_Register!$S$6:$S$35,"<>Closed") -> 0 | F30: =COUNTIFS(Risk_Register!$K$6:$K$35,5,Risk_Register!$L$6:$L$35,5,Risk_Register!$S$6:$S$35,"<>Closed") -> 0
A31: 4 | B31: =COUNTIFS(Risk_Register!$K$6:$K$35,1,Risk_Register!$L$6:$L$35,4,Risk_Register!$S$6:$S$35,"<>Closed") -> 1 | C31: =COUNTIFS(Risk_Register!$K$6:$K$35,2,Risk_Register!$L$6:$L$35,4,Risk_Register!$S$6:$S$35,"<>Closed") -> 3 | D31: =COUNTIFS(Risk_Register!$K$6:$K$35,3,Risk_Register!$L$6:$L$35,4,Risk_Register!$S$6:$S$35,"<>Closed") -> 0 | E31: =COUNTIFS(Risk_Register!$K$6:$K$35,4,Risk_Register!$L$6:$L$35,4,Risk_Register!$S$6:$S$35,"<>Closed") -> 0 | F31: =COUNTIFS(Risk_Register!$K$6:$K$35,5,Risk_Register!$L$6:$L$35,4,Risk_Register!$S$6:$S$35,"<>Closed") -> 0
A32: 3 | B32: =COUNTIFS(Risk_Register!$K$6:$K$35,1,Risk_Register!$L$6:$L$35,3,Risk_Register!$S$6:$S$35,"<>Closed") -> 0 | C32: =COUNTIFS(Risk_Register!$K$6:$K$35,2,Risk_Register!$L$6:$L$35,3,Risk_Register!$S$6:$S$35,"<>Closed") -> 3 | D32: =COUNTIFS(Risk_Register!$K$6:$K$35,3,Risk_Register!$L$6:$L$35,3,Risk_Register!$S$6:$S$35,"<>Closed") -> 3 | E32: =COUNTIFS(Risk_Register!$K$6:$K$35,4,Risk_Register!$L$6:$L$35,3,Risk_Register!$S$6:$S$35,"<>Closed") -> 0 | F32: =COUNTIFS(Risk_Register!$K$6:$K$35,5,Risk_Register!$L$6:$L$35,3,Risk_Register!$S$6:$S$35,"<>Closed") -> 0
A33: 2 | B33: =COUNTIFS(Risk_Register!$K$6:$K$35,1,Risk_Register!$L$6:$L$35,2,Risk_Register!$S$6:$S$35,"<>Closed") -> 0 | C33: =COUNTIFS(Risk_Register!$K$6:$K$35,2,Risk_Register!$L$6:$L$35,2,Risk_Register!$S$6:$S$35,"<>Closed") -> 1 | D33: =COUNTIFS(Risk_Register!$K$6:$K$35,3,Risk_Register!$L$6:$L$35,2,Risk_Register!$S$6:$S$35,"<>Closed") -> 0 | E33: =COUNTIFS(Risk_Register!$K$6:$K$35,4,Risk_Register!$L$6:$L$35,2,Risk_Register!$S$6:$S$35,"<>Closed") -> 0 | F33: =COUNTIFS(Risk_Register!$K$6:$K$35,5,Risk_Register!$L$6:$L$35,2,Risk_Register!$S$6:$S$35,"<>Closed") -> 0
A34: 1 | B34: =COUNTIFS(Risk_Register!$K$6:$K$35,1,Risk_Register!$L$6:$L$35,1,Risk_Register!$S$6:$S$35,"<>Closed") -> 0 | C34: =COUNTIFS(Risk_Register!$K$6:$K$35,2,Risk_Register!$L$6:$L$35,1,Risk_Register!$S$6:$S$35,"<>Closed") -> 0 | D34: =COUNTIFS(Risk_Register!$K$6:$K$35,3,Risk_Register!$L$6:$L$35,1,Risk_Register!$S$6:$S$35,"<>Closed") -> 0 | E34: =COUNTIFS(Risk_Register!$K$6:$K$35,4,Risk_Register!$L$6:$L$35,1,Risk_Register!$S$6:$S$35,"<>Closed") -> 0 | F34: =COUNTIFS(Risk_Register!$K$6:$K$35,5,Risk_Register!$L$6:$L$35,1,Risk_Register!$S$6:$S$35,"<>Closed") -> 0
A36: Vendor snapshot
A37: Vendor | B37: Inherent | C37: Control effectiveness | D37: Residual | E37: Recommended decision
A38: =IF(Vendor_Register!A6="","",Vendor_Register!B6) -> Stratus Cloud Infrastructure | B38: =IF(Vendor_Register!A6="","",Vendor_Register!M6) -> Critical | C38: =IF(Vendor_Register!A6="","",Vendor_Register!N6) -> 0.96153846 | D38: =IF(Vendor_Register!A6="","",Vendor_Register!Q6) -> Medium | E38: =IF(Vendor_Register!A6="","",Vendor_Register!R6) -> Approve with standard monitoring
A39: =IF(Vendor_Register!A7="","",Vendor_Register!B7) -> NimbusAI Language Platform | B39: =IF(Vendor_Register!A7="","",Vendor_Register!M7) -> High | C39: =IF(Vendor_Register!A7="","",Vendor_Register!N7) -> 0.81531532 | D39: =IF(Vendor_Register!A7="","",Vendor_Register!Q7) -> Medium | E39: =IF(Vendor_Register!A7="","",Vendor_Register!R7) -> Remediate critical gaps before approval
A40: =IF(Vendor_Register!A8="","",Vendor_Register!B8) -> Orbit CRM Suite | B40: =IF(Vendor_Register!A8="","",Vendor_Register!M8) -> High | C40: =IF(Vendor_Register!A8="","",Vendor_Register!N8) -> 0.51098901 | D40: =IF(Vendor_Register!A8="","",Vendor_Register!Q8) -> High | E40: =IF(Vendor_Register!A8="","",Vendor_Register!R8) -> Conditional approval with remediation plan
A41: =IF(Vendor_Register!A9="","",Vendor_Register!B9) -> InsightML Analytics | B41: =IF(Vendor_Register!A9="","",Vendor_Register!M9) -> Medium | C41: =IF(Vendor_Register!A9="","",Vendor_Register!N9) -> 0.74324324 | D41: =IF(Vendor_Register!A9="","",Vendor_Register!Q9) -> Low | E41: =IF(Vendor_Register!A9="","",Vendor_Register!R9) -> Approve
A42: =IF(Vendor_Register!A10="","",Vendor_Register!B10) -> Cirrus Backup & Recovery | B42: =IF(Vendor_Register!A10="","",Vendor_Register!M10) -> High | C42: =IF(Vendor_Register!A10="","",Vendor_Register!N10) -> 0.95604396 | D42: =IF(Vendor_Register!A10="","",Vendor_Register!Q10) -> Low | E42: =IF(Vendor_Register!A10="","",Vendor_Register!R10) -> Approve
A43: =IF(Vendor_Register!A11="","",Vendor_Register!B11) -> Brightleaf Survey Tool | B43: =IF(Vendor_Register!A11="","",Vendor_Register!M11) -> Low | C43: =IF(Vendor_Register!A11="","",Vendor_Register!N11) -> 0.58791209 | D43: =IF(Vendor_Register!A11="","",Vendor_Register!Q11) -> Low | E43: =IF(Vendor_Register!A11="","",Vendor_Register!R11) -> Approve
A44: =IF(Vendor_Register!A12="","",Vendor_Register!B12) | B44: =IF(Vendor_Register!A12="","",Vendor_Register!M12) | C44: =IF(Vendor_Register!A12="","",Vendor_Register!N12) | D44: =IF(Vendor_Register!A12="","",Vendor_Register!Q12) | E44: =IF(Vendor_Register!A12="","",Vendor_Register!R12)
A45: =IF(Vendor_Register!A13="","",Vendor_Register!B13) | B45: =IF(Vendor_Register!A13="","",Vendor_Register!M13) | C45: =IF(Vendor_Register!A13="","",Vendor_Register!N13) | D45: =IF(Vendor_Register!A13="","",Vendor_Register!Q13) | E45: =IF(Vendor_Register!A13="","",Vendor_Register!R13)
A46: =IF(Vendor_Register!A14="","",Vendor_Register!B14) | B46: =IF(Vendor_Register!A14="","",Vendor_Register!M14) | C46: =IF(Vendor_Register!A14="","",Vendor_Register!N14) | D46: =IF(Vendor_Register!A14="","",Vendor_Register!Q14) | E46: =IF(Vendor_Register!A14="","",Vendor_Register!R14)
A47: =IF(Vendor_Register!A15="","",Vendor_Register!B15) | B47: =IF(Vendor_Register!A15="","",Vendor_Register!M15) | C47: =IF(Vendor_Register!A15="","",Vendor_Register!N15) | D47: =IF(Vendor_Register!A15="","",Vendor_Register!Q15) | E47: =IF(Vendor_Register!A15="","",Vendor_Register!R15)

Sheet Vendor_Register
A1: Vendor Register – Inherent & Residual Risk
A2: Sample organization: Meridian Analytics Group (fictional). Vendors are fictional. Enter the 6 factor scores (1–5); everything else calculates.
A5: Vendor ID | B5: Vendor name | C5: Service provided | D5: Category | E5: Business owner | F5: Data sensitivity (1–5) | G5: Business criticality (1–5) | H5: System / network access (1–5) | I5: Regulatory exposure (1–5) | J5: Substitutability (1–5) | K5: AI impact (1–5) | L5: Inherent score (20–100) | M5: Inherent rating | N5: Control effectiveness | O5: Critical gaps | P5: Residual score | Q5: Residual rating | R5: Recommended decision | S5: Required approver | T5: Approval status | U5: Last assessment | V5: Review cycle (months) | W5: Next review due | X5: Review status | Y5: Contract renewal | Z5: Notes
A6: V-001 | B6: Stratus Cloud Infrastructure | C6: IaaS/PaaS hosting for production workloads and databases | D6: Cloud Infrastructure (IaaS/PaaS) | E6: Head of Infrastructure | F6: 5 | G6: 5 | H6: 5 | I6: 4 | J6: 4 | K6: 1 | L6: =IF($A6="","",ROUND((F6*Methodology!$B$10+G6*Methodology!$B$11+H6*Methodology!$B$12+I6*Methodology!$B$13+J6*Methodology!$B$14+K6*Methodology!$B$15)/Methodology!$B$16*Methodology!$B$6,1)) -> 88 | M6: =IF($A6="","",INDEX(Methodology!$A$20:$A$23,MATCH(L6,Methodology!$B$20:$B$23,1))) -> Critical | N6: =IF($A6="","",IFERROR(INDEX(Assessment_Results!$C$6:$C$15,MATCH($A6,Assessment_Results!$A$6:$A$15,0)),"")) -> 0.96153846 | O6: =IF($A6="","",IFERROR(INDEX(Assessment_Results!$E$6:$E$15,MATCH($A6,Assessment_Results!$A$6:$A$15,0)),"")) -> 0 | P6: =IF(OR($A6="",N6=""),"",ROUND(L6*(1-N6*Methodology!$B$5),1)) -> 28.8 | Q6: =IF(P6="","",INDEX(Methodology!$A$20:$A$23,MATCH(P6,Methodology!$C$20:$C$23,1))) -> Medium | R6: =IF($A6="","",IF(N6="","Assessment pending",IF(O6>0,"Remediate critical gaps before approval",IF(Q6="Critical","Escalate: executive risk acceptance required",IF(Q6="High","Conditional approval with remediation plan",IF(Q6="Medium","Approve with standard monitoring","Approve")))))) -> Approve with standard monitoring | S6: =IF($A6="","",IF(Q6="","Pending assessment",INDEX(Approval_Workflow!$B$20:$B$23,MATCH(Q6,Approval_Workflow!$A$20:$A$23,0)))) -> Business Owner + Information Security Manager | T6: Approved | U6: 46093 | V6: =IF($A6="","",INDEX(Methodology!$D$20:$D$23,MATCH(M6,Methodology!$A$20:$A$23,0))) -> 12 | W6: =IF(OR($A6="",U6=""),"",EDATE(U6,V6)) -> 46458 | X6: =IF(W6="","",IF(W6<Methodology!$B$4,"Overdue",IF(W6-Methodology!$B$4<=90,"Due within 90 days","On schedule"))) -> On schedule | Y6: 46568
A7: V-002 | B7: NimbusAI Language Platform | C7: Hosted large-language-model API embedded in the customer support assistant | D7: AI/ML Software | E7: Director of Customer Support | F7: 5 | G7: 3 | H7: 3 | I7: 4 | J7: 2 | K7: 5 | L7: =IF($A7="","",ROUND((F7*Methodology!$B$10+G7*Methodology!$B$11+H7*Methodology!$B$12+I7*Methodology!$B$13+J7*Methodology!$B$14+K7*Methodology!$B$15)/Methodology!$B$16*Methodology!$B$6,1)) -> 76 | M7: =IF($A7="","",INDEX(Methodology!$A$20:$A$23,MATCH(L7,Methodology!$B$20:$B$23,1))) -> High | N7: =IF($A7="","",IFERROR(INDEX(Assessment_Results!$C$6:$C$15,MATCH($A7,Assessment_Results!$A$6:$A$15,0)),"")) -> 0.81531532 | O7: =IF($A7="","",IFERROR(INDEX(Assessment_Results!$E$6:$E$15,MATCH($A7,Assessment_Results!$A$6:$A$15,0)),"")) -> 1 | P7: =IF(OR($A7="",N7=""),"",ROUND(L7*(1-N7*Methodology!$B$5),1)) -> 32.6 | Q7: =IF(P7="","",INDEX(Methodology!$A$20:$A$23,MATCH(P7,Methodology!$C$20:$C$23,1))) -> Medium | R7: =IF($A7="","",IF(N7="","Assessment pending",IF(O7>0,"Remediate critical gaps before approval",IF(Q7="Critical","Escalate: executive risk acceptance required",IF(Q7="High","Conditional approval with remediation plan",IF(Q7="Medium","Approve with standard monitoring","Approve")))))) -> Remediate critical gaps before approval | S7: =IF($A7="","",IF(Q7="","Pending assessment",INDEX(Approval_Workflow!$B$20:$B$23,MATCH(Q7,Approval_Workflow!$A$20:$A$23,0)))) -> Business Owner + Information Security Manager | T7: Under Review | V7: =IF($A7="","",INDEX(Methodology!$D$20:$D$23,MATCH(M7,Methodology!$A$20:$A$23,0))) -> 18 | W7: =IF(OR($A7="",U7=""),"",EDATE(U7,V7)) | X7: =IF(W7="","",IF(W7<Methodology!$B$4,"Overdue",IF(W7-Methodology!$B$4<=90,"Due within 90 days","On schedule"))) | Y7: 46675 | Z7: Pending approval: critical gap on AI data-use commitment (see Risk_Register VR-004).
A8: V-003 | B8: Orbit CRM Suite | C8: SaaS CRM storing customer contact and contract data | D8: SaaS Application | E8: VP Sales | F8: 4 | G8: 4 | H8: 3 | I8: 3 | J8: 3 | K8: 1 | L8: =IF($A8="","",ROUND((F8*Methodology!$B$10+G8*Methodology!$B$11+H8*Methodology!$B$12+I8*Methodology!$B$13+J8*Methodology!$B$14+K8*Methodology!$B$15)/Methodology!$B$16*Methodology!$B$6,1)) -> 67 | M8: =IF($A8="","",INDEX(Methodology!$A$20:$A$23,MATCH(L8,Methodology!$B$20:$B$23,1))) -> High | N8: =IF($A8="","",IFERROR(INDEX(Assessment_Results!$C$6:$C$15,MATCH($A8,Assessment_Results!$A$6:$A$15,0)),"")) -> 0.51098901 | O8: =IF($A8="","",IFERROR(INDEX(Assessment_Results!$E$6:$E$15,MATCH($A8,Assessment_Results!$A$6:$A$15,0)),"")) -> 0 | P8: =IF(OR($A8="",N8=""),"",ROUND(L8*(1-N8*Methodology!$B$5),1)) -> 43 | Q8: =IF(P8="","",INDEX(Methodology!$A$20:$A$23,MATCH(P8,Methodology!$C$20:$C$23,1))) -> High | R8: =IF($A8="","",IF(N8="","Assessment pending",IF(O8>0,"Remediate critical gaps before approval",IF(Q8="Critical","Escalate: executive risk acceptance required",IF(Q8="High","Conditional approval with remediation plan",IF(Q8="Medium","Approve with standard monitoring","Approve")))))) -> Conditional approval with remediation plan | S8: =IF($A8="","",IF(Q8="","Pending assessment",INDEX(Approval_Workflow!$B$20:$B$23,MATCH(Q8,Approval_Workflow!$A$20:$A$23,0)))) -> Information Security Manager + Privacy/Legal + Head of Business Unit | T8: Conditionally Approved | U8: 45920 | V8: =IF($A8="","",INDEX(Methodology!$D$20:$D$23,MATCH(M8,Methodology!$A$20:$A$23,0))) -> 18 | W8: =IF(OR($A8="",U8=""),"",EDATE(U8,V8)) -> 46466 | X8: =IF(W8="","",IF(W8<Methodology!$B$4,"Overdue",IF(W8-Methodology!$B$4<=90,"Due within 90 days","On schedule"))) -> On schedule | Y8: 46630 | Z8: Attestation expired; remediation plan agreed with vendor.
A9: V-004 | B9: InsightML Analytics | C9: AI-driven usage analytics and churn-prediction service | D9: AI/ML Software | E9: Head of Data Science | F9: 3 | G9: 2 | H9: 2 | I9: 2 | J9: 2 | K9: 4 | L9: =IF($A9="","",ROUND((F9*Methodology!$B$10+G9*Methodology!$B$11+H9*Methodology!$B$12+I9*Methodology!$B$13+J9*Methodology!$B$14+K9*Methodology!$B$15)/Methodology!$B$16*Methodology!$B$6,1)) -> 50 | M9: =IF($A9="","",INDEX(Methodology!$A$20:$A$23,MATCH(L9,Methodology!$B$20:$B$23,1))) -> Medium | N9: =IF($A9="","",IFERROR(INDEX(Assessment_Results!$C$6:$C$15,MATCH($A9,Assessment_Results!$A$6:$A$15,0)),"")) -> 0.74324324 | O9: =IF($A9="","",IFERROR(INDEX(Assessment_Results!$E$6:$E$15,MATCH($A9,Assessment_Results!$A$6:$A$15,0)),"")) -> 0 | P9: =IF(OR($A9="",N9=""),"",ROUND(L9*(1-N9*Methodology!$B$5),1)) -> 24 | Q9: =IF(P9="","",INDEX(Methodology!$A$20:$A$23,MATCH(P9,Methodology!$C$20:$C$23,1))) -> Low | R9: =IF($A9="","",IF(N9="","Assessment pending",IF(O9>0,"Remediate critical gaps before approval",IF(Q9="Critical","Escalate: executive risk acceptance required",IF(Q9="High","Conditional approval with remediation plan",IF(Q9="Medium","Approve with standard monitoring","Approve")))))) -> Approve | S9: =IF($A9="","",IF(Q9="","Pending assessment",INDEX(Approval_Workflow!$B$20:$B$23,MATCH(Q9,Approval_Workflow!$A$20:$A$23,0)))) -> Business Owner + GRC Analyst | T9: Approved | U9: 45519 | V9: =IF($A9="","",INDEX(Methodology!$D$20:$D$23,MATCH(M9,Methodology!$A$20:$A$23,0))) -> 24 | W9: =IF(OR($A9="",U9=""),"",EDATE(U9,V9)) -> 46249 | X9: =IF(W9="","",IF(W9<Methodology!$B$4,"Overdue",IF(W9-Methodology!$B$4<=90,"Due within 90 days","On schedule"))) -> Overdue | Y9: 46507 | Z9: Full reassessment overdue; scheduled for Q4.
A10: V-005 | B10: Cirrus Backup & Recovery | C10: Cloud backup and disaster-recovery service | D10: SaaS Application | E10: IT Operations Manager | F10: 4 | G10: 4 | H10: 2 | I10: 3 | J10: 3 | K10: 1 | L10: =IF($A10="","",ROUND((F10*Methodology!$B$10+G10*Methodology!$B$11+H10*Methodology!$B$12+I10*Methodology!$B$13+J10*Methodology!$B$14+K10*Methodology!$B$15)/Methodology!$B$16*Methodology!$B$6,1)) -> 64 | M10: =IF($A10="","",INDEX(Methodology!$A$20:$A$23,MATCH(L10,Methodology!$B$20:$B$23,1))) -> High | N10: =IF($A10="","",IFERROR(INDEX(Assessment_Results!$C$6:$C$15,MATCH($A10,Assessment_Results!$A$6:$A$15,0)),"")) -> 0.95604396 | O10: =IF($A10="","",IFERROR(INDEX(Assessment_Results!$E$6:$E$15,MATCH($A10,Assessment_Results!$A$6:$A$15,0)),"")) -> 0 | P10: =IF(OR($A10="",N10=""),"",ROUND(L10*(1-N10*Methodology!$B$5),1)) -> 21.2 | Q10: =IF(P10="","",INDEX(Methodology!$A$20:$A$23,MATCH(P10,Methodology!$C$20:$C$23,1))) -> Low | R10: =IF($A10="","",IF(N10="","Assessment pending",IF(O10>0,"Remediate critical gaps before approval",IF(Q10="Critical","Escalate: executive risk acceptance required",IF(Q10="High","Conditional approval with remediation plan",IF(Q10="Medium","Approve with standard monitoring","Approve")))))) -> Approve | S10: =IF($A10="","",IF(Q10="","Pending assessment",INDEX(Approval_Workflow!$B$20:$B$23,MATCH(Q10,Approval_Workflow!$A$20:$A$23,0)))) -> Business Owner + GRC Analyst | T10: Approved | U10: 45782 | V10: =IF($A10="","",INDEX(Methodology!$D$20:$D$23,MATCH(M10,Methodology!$A$20:$A$23,0))) -> 18 | W10: =IF(OR($A10="",U10=""),"",EDATE(U10,V10)) -> 46331 | X10: =IF(W10="","",IF(W10<Methodology!$B$4,"Overdue",IF(W10-Methodology!$B$4<=90,"Due within 90 days","On schedule"))) -> Due within 90 days | Y10: 46538
A11: V-006 | B11: Brightleaf Survey Tool | C11: Online survey platform for employee and customer feedback | D11: SaaS Application | E11: Marketing Manager | F11: 2 | G11: 2 | H11: 1 | I11: 2 | J11: 1 | K11: 1 | L11: =IF($A11="","",ROUND((F11*Methodology!$B$10+G11*Methodology!$B$11+H11*Methodology!$B$12+I11*Methodology!$B$13+J11*Methodology!$B$14+K11*Methodology!$B$15)/Methodology!$B$16*Methodology!$B$6,1)) -> 33 | M11: =IF($A11="","",INDEX(Methodology!$A$20:$A$23,MATCH(L11,Methodology!$B$20:$B$23,1))) -> Low | N11: =IF($A11="","",IFERROR(INDEX(Assessment_Results!$C$6:$C$15,MATCH($A11,Assessment_Results!$A$6:$A$15,0)),"")) -> 0.58791209 | O11: =IF($A11="","",IFERROR(INDEX(Assessment_Results!$E$6:$E$15,MATCH($A11,Assessment_Results!$A$6:$A$15,0)),"")) -> 0 | P11: =IF(OR($A11="",N11=""),"",ROUND(L11*(1-N11*Methodology!$B$5),1)) -> 19.4 | Q11: =IF(P11="","",INDEX(Methodology!$A$20:$A$23,MATCH(P11,Methodology!$C$20:$C$23,1))) -> Low | R11: =IF($A11="","",IF(N11="","Assessment pending",IF(O11>0,"Remediate critical gaps before approval",IF(Q11="Critical","Escalate: executive risk acceptance required",IF(Q11="High","Conditional approval with remediation plan",IF(Q11="Medium","Approve with standard monitoring","Approve")))))) -> Approve | S11: =IF($A11="","",IF(Q11="","Pending assessment",INDEX(Approval_Workflow!$B$20:$B$23,MATCH(Q11,Approval_Workflow!$A$20:$A$23,0)))) -> Business Owner + GRC Analyst | T11: Approved | U11: 45323 | V11: =IF($A11="","",INDEX(Methodology!$D$20:$D$23,MATCH(M11,Methodology!$A$20:$A$23,0))) -> 36 | W11: =IF(OR($A11="",U11=""),"",EDATE(U11,V11)) -> 46419 | X11: =IF(W11="","",IF(W11<Methodology!$B$4,"Overdue",IF(W11-Methodology!$B$4<=90,"Due within 90 days","On schedule"))) -> On schedule | Y11: 46477
L12: =IF($A12="","",ROUND((F12*Methodology!$B$10+G12*Methodology!$B$11+H12*Methodology!$B$12+I12*Methodology!$B$13+J12*Methodology!$B$14+K12*Methodology!$B$15)/Methodology!$B$16*Methodology!$B$6,1)) | M12: =IF($A12="","",INDEX(Methodology!$A$20:$A$23,MATCH(L12,Methodology!$B$20:$B$23,1))) | N12: =IF($A12="","",IFERROR(INDEX(Assessment_Results!$C$6:$C$15,MATCH($A12,Assessment_Results!$A$6:$A$15,0)),"")) | O12: =IF($A12="","",IFERROR(INDEX(Assessment_Results!$E$6:$E$15,MATCH($A12,Assessment_Results!$A$6:$A$15,0)),"")) | P12: =IF(OR($A12="",N12=""),"",ROUND(L12*(1-N12*Methodology!$B$5),1)) | Q12: =IF(P12="","",INDEX(Methodology!$A$20:$A$23,MATCH(P12,Methodology!$C$20:$C$23,1))) | R12: =IF($A12="","",IF(N12="","Assessment pending",IF(O12>0,"Remediate critical gaps before approval",IF(Q12="Critical","Escalate: executive risk acceptance required",IF(Q12="High","Conditional approval with remediation plan",IF(Q12="Medium","Approve with standard monitoring","Approve")))))) | S12: =IF($A12="","",IF(Q12="","Pending assessment",INDEX(Approval_Workflow!$B$20:$B$23,MATCH(Q12,Approval_Workflow!$A$20:$A$23,0)))) | V12: =IF($A12="","",INDEX(Methodology!$D$20:$D$23,MATCH(M12,Methodology!$A$20:$A$23,0))) | W12: =IF(OR($A12="",U12=""),"",EDATE(U12,V12)) | X12: =IF(W12="","",IF(W12<Methodology!$B$4,"Overdue",IF(W12-Methodology!$B$4<=90,"Due within 90 days","On schedule")))
L13: =IF($A13="","",ROUND((F13*Methodology!$B$10+G13*Methodology!$B$11+H13*Methodology!$B$12+I13*Methodology!$B$13+J13*Methodology!$B$14+K13*Methodology!$B$15)/Methodology!$B$16*Methodology!$B$6,1)) | M13: =IF($A13="","",INDEX(Methodology!$A$20:$A$23,MATCH(L13,Methodology!$B$20:$B$23,1))) | N13: =IF($A13="","",IFERROR(INDEX(Assessment_Results!$C$6:$C$15,MATCH($A13,Assessment_Results!$A$6:$A$15,0)),"")) | O13: =IF($A13="","",IFERROR(INDEX(Assessment_Results!$E$6:$E$15,MATCH($A13,Assessment_Results!$A$6:$A$15,0)),"")) | P13: =IF(OR($A13="",N13=""),"",ROUND(L13*(1-N13*Methodology!$B$5),1)) | Q13: =IF(P13="","",INDEX(Methodology!$A$20:$A$23,MATCH(P13,Methodology!$C$20:$C$23,1))) | R13: =IF($A13="","",IF(N13="","Assessment pending",IF(O13>0,"Remediate critical gaps before approval",IF(Q13="Critical","Escalate: executive risk acceptance required",IF(Q13="High","Conditional approval with remediation plan",IF(Q13="Medium","Approve with standard monitoring","Approve")))))) | S13: =IF($A13="","",IF(Q13="","Pending assessment",INDEX(Approval_Workflow!$B$20:$B$23,MATCH(Q13,Approval_Workflow!$A$20:$A$23,0)))) | V13: =IF($A13="","",INDEX(Methodology!$D$20:$D$23,MATCH(M13,Methodology!$A$20:$A$23,0))) | W13: =IF(OR($A13="",U13=""),"",EDATE(U13,V13)) | X13: =IF(W13="","",IF(W13<Methodology!$B$4,"Overdue",IF(W13-Methodology!$B$4<=90,"Due within 90 days","On schedule")))
L14: =IF($A14="","",ROUND((F14*Methodology!$B$10+G14*Methodology!$B$11+H14*Methodology!$B$12+I14*Methodology!$B$13+J14*Methodology!$B$14+K14*Methodology!$B$15)/Methodology!$B$16*Methodology!$B$6,1)) | M14: =IF($A14="","",INDEX(Methodology!$A$20:$A$23,MATCH(L14,Methodology!$B$20:$B$23,1))) | N14: =IF($A14="","",IFERROR(INDEX(Assessment_Results!$C$6:$C$15,MATCH($A14,Assessment_Results!$A$6:$A$15,0)),"")) | O14: =IF($A14="","",IFERROR(INDEX(Assessment_Results!$E$6:$E$15,MATCH($A14,Assessment_Results!$A$6:$A$15,0)),"")) | P14: =IF(OR($A14="",N14=""),"",ROUND(L14*(1-N14*Methodology!$B$5),1)) | Q14: =IF(P14="","",INDEX(Methodology!$A$20:$A$23,MATCH(P14,Methodology!$C$20:$C$23,1))) | R14: =IF($A14="","",IF(N14="","Assessment pending",IF(O14>0,"Remediate critical gaps before approval",IF(Q14="Critical","Escalate: executive risk acceptance required",IF(Q14="High","Conditional approval with remediation plan",IF(Q14="Medium","Approve with standard monitoring","Approve")))))) | S14: =IF($A14="","",IF(Q14="","Pending assessment",INDEX(Approval_Workflow!$B$20:$B$23,MATCH(Q14,Approval_Workflow!$A$20:$A$23,0)))) | V14: =IF($A14="","",INDEX(Methodology!$D$20:$D$23,MATCH(M14,Methodology!$A$20:$A$23,0))) | W14: =IF(OR($A14="",U14=""),"",EDATE(U14,V14)) | X14: =IF(W14="","",IF(W14<Methodology!$B$4,"Overdue",IF(W14-Methodology!$B$4<=90,"Due within 90 days","On schedule")))
L15: =IF($A15="","",ROUND((F15*Methodology!$B$10+G15*Methodology!$B$11+H15*Methodology!$B$12+I15*Methodology!$B$13+J15*Methodology!$B$14+K15*Methodology!$B$15)/Methodology!$B$16*Methodology!$B$6,1)) | M15: =IF($A15="","",INDEX(Methodology!$A$20:$A$23,MATCH(L15,Methodology!$B$20:$B$23,1))) | N15: =IF($A15="","",IFERROR(INDEX(Assessment_Results!$C$6:$C$15,MATCH($A15,Assessment_Results!$A$6:$A$15,0)),"")) | O15: =IF($A15="","",IFERROR(INDEX(Assessment_Results!$E$6:$E$15,MATCH($A15,Assessment_Results!$A$6:$A$15,0)),"")) | P15: =IF(OR($A15="",N15=""),"",ROUND(L15*(1-N15*Methodology!$B$5),1)) | Q15: =IF(P15="","",INDEX(Methodology!$A$20:$A$23,MATCH(P15,Methodology!$C$20:$C$23,1))) | R15: =IF($A15="","",IF(N15="","Assessment pending",IF(O15>0,"Remediate critical gaps before approval",IF(Q15="Critical","Escalate: executive risk acceptance required",IF(Q15="High","Conditional approval with remediation plan",IF(Q15="Medium","Approve with standard monitoring","Approve")))))) | S15: =IF($A15="","",IF(Q15="","Pending assessment",INDEX(Approval_Workflow!$B$20:$B$23,MATCH(Q15,Approval_Workflow!$A$20:$A$23,0)))) | V15: =IF($A15="","",INDEX(Methodology!$D$20:$D$23,MATCH(M15,Methodology!$A$20:$A$23,0))) | W15: =IF(OR($A15="",U15=""),"",EDATE(U15,V15)) | X15: =IF(W15="","",IF(W15<Methodology!$B$4,"Overdue",IF(W15-Methodology!$B$4<=90,"Due within 90 days","On schedule")))
A17: Legend: blue text on yellow = input; black = formula. Inherent rating drives review cycle and monitoring tier; residual rating drives the approval authority.

Sheet Methodology
A1: Scoring Methodology & Assumptions
A2: All scoring parameters live here. Blue cells on a yellow fill are editable; every other sheet recalculates from them.
A3: 1. Program parameters
A4: Assessment as-of date | B4: 46320 | C4: Reference date for 'overdue' and 'due soon' flags. Replace with =TODAY() for live tracking.
A5: Maximum risk reduction from controls | B5: 0.7 | C5: Assumption: even perfect vendor controls cannot remove more than 70% of inherent risk (residual risk never reaches zero).
A6: Inherent score scale factor | B6: 20 | C6: Weighted average of factor scores (1–5) × 20 produces a 20–100 inherent risk score.
A8: 2. Inherent risk factors & weights (score each vendor 1–5 per factor)
A9: Factor | B9: Weight | C9: 1 – Minimal | D9: 2 – Low | E9: 3 – Moderate | F9: 4 – High | G9: 5 – Severe
A10: Data sensitivity | B10: 0.3 | C10: No data shared, or public data only | D10: Internal, non-sensitive data | E10: Confidential business data | F10: Personal data (PII) or financial data | G10: Special-category data, PHI, payment card data, credentials or crown-jewel IP at scale
A11: Business criticality | B11: 0.25 | C11: Convenience tool; no impact if unavailable | D11: Minor disruption; manual workaround exists | E11: Degraded operations beyond one business day | F11: Significant revenue or customer impact within hours | G11: Mission-critical; outage stops core service within 4 hours
A12: System / network access | B12: 0.15 | C12: No access to systems or networks | D12: Limited read-only access to non-sensitive systems | E12: Standard user or API access to internal systems | F12: Privileged or integrated access to production systems | G12: Hosts or administers production environment; network-level trust
A13: Regulatory exposure | B13: 0.1 | C13: No regulatory relevance | D13: Minor contractual or policy requirements | E13: General privacy law applies | F13: Regulated data or activity (GDPR, HIPAA, PCI DSS, SOX) | G13: Multiple regimes; high penalties; regulator scrutiny
A14: Substitutability (lock-in) | B14: 0.1 | C14: Many alternatives; switch in under 1 month | D14: Alternatives exist; switch in 1–3 months | E14: Few alternatives; 3–6 months to switch | F14: Very few alternatives; 6+ months to migrate | G14: Sole source or locked in; no practical alternative
A15: AI impact | B15: 0.1 | C15: No AI/ML functionality | D15: Embedded AI for low-risk convenience features | E15: AI informs internal decisions with human review | F15: AI processes sensitive data or shapes customer-facing outcomes | G15: Autonomous or high-impact AI decisions affecting individuals (possible EU AI Act high-risk use)
A16: Total weight (must equal 100%) | B16: =SUM(B10:B15) -> 1 | C16: =IF(ROUND(B16,4)=1,"OK","ERROR: weights must total 100%") -> OK
A18: 3. Rating bands, review cadence & monitoring intervals
A19: Rating | B19: Inherent score ≥ | C19: Residual score ≥ | D19: Full reassessment (months) | E19: Interim check (months; 0 = at renewal) | F19: Treatment
A20: Low | B20: 0 | C20: 0 | D20: 36 | E20: 0 | F20: Streamlined assessment; standard onboarding; monitor at renewal.
A21: Medium | B21: 40 | C21: 25 | D21: 24 | E21: 12 | F21: Full questionnaire; annual attestation; standard monitoring.
A22: High | B22: 60 | C22: 40 | D22: 18 | E22: 6 | F22: Full assessment with evidence validation; semi-annual checks; remediation plan required for gaps.
A23: Critical | B23: 80 | C23: 60 | D23: 12 | E23: 3 | F23: Enhanced due diligence; quarterly checks; executive approval and exit plan required.
A24: Bands must stay in ascending order (Low → Critical). Residual thresholds are lower than inherent thresholds because residual scores are reduced by control effectiveness.
A25: 4. Questionnaire response values
A26: Response | B26: Value | C26: Treatment in scoring
A27: Yes | B27: 1 | C27: Control fully implemented and evidenced
A28: Partial | B28: 0.5 | C28: Partially implemented, planned, or evidence incomplete
A29: No | B29: 0 | C29: Control absent
A30: N/A | B30: Excluded | C30: Not applicable; removed from numerator and denominator
A32: 5. How the scores are calculated
A33: Inherent Risk Score = Σ(factor score × weight) ÷ Σ(weights) × scale factor → range 20–100.
A34: Control Effectiveness (CE) = Σ(question weight × response value) ÷ Σ(question weight of answered, applicable questions) → 0–100%.
A35: Residual Risk Score = Inherent Risk Score × (1 − CE × maximum risk reduction).
A36: Critical controls answered 'No' are counted as critical gaps and block approval until remediated or formally accepted, regardless of the residual score.
A37: Rating = lookup of the score against the band thresholds in section 3.
A39: 6. Risk Register 5×5 scale (likelihood × impact)
A40: Score | B40: Likelihood | C40: Description
A41: 1 | B41: Rare | C41: Less than 5% chance within 12 months
A42: 2 | B42: Unlikely | C42: 5–20% chance within 12 months
A43: 3 | B43: Possible | C43: 20–50% chance within 12 months
A44: 4 | B44: Likely | C44: 50–80% chance within 12 months
A45: 5 | B45: Almost certain | C45: More than 80% chance within 12 months
A47: Score | B47: Impact | C47: Description (illustrative; calibrate to your risk appetite)
A48: 1 | B48: Negligible | C48: Under $10k; no data exposure; no regulatory interest
A49: 2 | B49: Minor | C49: $10k–$50k; limited internal data exposure; disruption under 4 hours
A50: 3 | B50: Moderate | C50: $50k–$250k; limited personal data; 4–24 hours disruption; regulatory enquiry possible
A51: 4 | B51: Major | C51: $250k–$1M; significant personal data breach; 1–3 days outage; regulatory action likely
A52: 5 | B52: Severe | C52: Over $1M; large-scale breach; outage over 3 days; major litigation or loss of licence
A54: Rating | B54: Score (L × I) ≥
A55: Low | B55: 1
A56: Medium | B56: 5
A57: High | B57: 10
A58: Critical | B58: 17

Sheet Questionnaire
A1: Vendor Security & Risk Questionnaire
A2: Complete one response column per vendor (Yes / Partial / No / N/A). Weighted scoring feeds Assessment_Results. Sample responses are fictional.
I3: Vendor ID → | J3: =IF(Vendor_Register!$A6="","",Vendor_Register!$A6) -> V-001 | K3: =IF(Vendor_Register!$A7="","",Vendor_Register!$A7) -> V-002 | L3: =IF(Vendor_Register!$A8="","",Vendor_Register!$A8) -> V-003 | M3: =IF(Vendor_Register!$A9="","",Vendor_Register!$A9) -> V-004 | N3: =IF(Vendor_Register!$A10="","",Vendor_Register!$A10) -> V-005 | O3: =IF(Vendor_Register!$A11="","",Vendor_Register!$A11) -> V-006 | P3: =IF(Vendor_Register!$A12="","",Vendor_Register!$A12) | Q3: =IF(Vendor_Register!$A13="","",Vendor_Register!$A13) | R3: =IF(Vendor_Register!$A14="","",Vendor_Register!$A14) | S3: =IF(Vendor_Register!$A15="","",Vendor_Register!$A15)
A4: Q ID | B4: Domain | C4: Question | D4: Applies to | E4: Weight (1–3) | F4: Critical control | G4: ISO/IEC 27001:2022 / 42001 reference | H4: NIST CSF 2.0 / AI RMF reference | I4: Evidence expected | J4: =IF(Vendor_Register!$B6="","(unused)",Vendor_Register!$B6) -> Stratus Cloud Infrastructure | K4: =IF(Vendor_Register!$B7="","(unused)",Vendor_Register!$B7) -> NimbusAI Language Platform | L4: =IF(Vendor_Register!$B8="","(unused)",Vendor_Register!$B8) -> Orbit CRM Suite | M4: =IF(Vendor_Register!$B9="","(unused)",Vendor_Register!$B9) -> InsightML Analytics | N4: =IF(Vendor_Register!$B10="","(unused)",Vendor_Register!$B10) -> Cirrus Backup & Recovery | O4: =IF(Vendor_Register!$B11="","(unused)",Vendor_Register!$B11) -> Brightleaf Survey Tool | P4: =IF(Vendor_Register!$B12="","(unused)",Vendor_Register!$B12) -> (unused) | Q4: =IF(Vendor_Register!$B13="","(unused)",Vendor_Register!$B13) -> (unused) | R4: =IF(Vendor_Register!$B14="","(unused)",Vendor_Register!$B14) -> (unused) | S4: =IF(Vendor_Register!$B15="","(unused)",Vendor_Register!$B15) -> (unused)
A5: GOV-01 | B5: Governance & Risk Management | C5: Does the vendor maintain a documented information security policy, approved by management and reviewed at least annually? | D5: All | E5: 3 | F5: No | G5: ISO 27001 A.5.1 | H5: CSF GV.PO | I5: Policy document with approval and review history | J5: Yes | K5: Yes | L5: Partial | M5: Yes | N5: Yes | O5: Partial
A6: GOV-02 | B6: Governance & Risk Management | C6: Does the vendor hold a current independent attestation or certification (ISO/IEC 27001 or SOC 2 Type II) covering the in-scope services? | D6: All | E6: 3 | F6: Yes | G6: ISO 27001 Cl. 9.2, A.5.35 | H6: CSF GV.SC-07 | I6: Certificate or SOC 2 report: scope, period, exceptions | J6: Yes | K6: Partial | L6: Yes | M6: Partial | N6: Yes | O6: Partial
A7: GOV-03 | B7: Governance & Risk Management | C7: Is there a named executive accountable for information security (CISO or equivalent) and a dedicated security function? | D7: All | E7: 2 | F7: No | G7: ISO 27001 A.5.2 | H7: CSF GV.RR | I7: Organization chart; security team description | J7: Yes | K7: Yes | L7: No | M7: Partial | N7: Yes | O7: No
A8: GOV-04 | B8: Governance & Risk Management | C8: Does the vendor perform formal information security risk assessments at least annually and track risks to closure? | D8: All | E8: 2 | F8: No | G8: ISO 27001 Cl. 6.1.2 | H8: CSF ID.RA | I8: Risk assessment methodology and sample register | J8: Partial | K8: Yes | L8: Partial | M8: Partial | N8: Partial | O8: No
A9: GOV-05 | B9: Governance & Risk Management | C9: Do all personnel complete security awareness training at onboarding and annually, with background screening where legally permitted? | D9: All | E9: 2 | F9: No | G9: ISO 27001 A.6.1, A.6.3 | H9: CSF PR.AT | I9: Training records; screening policy | J9: Yes | K9: Yes | L9: Partial | M9: Yes | N9: Yes | O9: Yes
A10: IAM-01 | B10: Identity & Access Management | C10: Is multi-factor authentication enforced for all workforce access to in-scope systems and for all privileged or administrative access? | D10: All | E10: 3 | F10: Yes | G10: ISO 27001 A.5.17, A.8.5 | H10: CSF PR.AA | I10: MFA policy; configuration screenshots | J10: Yes | K10: Yes | L10: Yes | M10: Yes | N10: Yes | O10: Yes
A11: IAM-02 | B11: Identity & Access Management | C11: Is access granted on least-privilege, role-based principles with documented approval and reviewed at least quarterly? | D11: All | E11: 2 | F11: No | G11: ISO 27001 A.5.15, A.5.18 | H11: CSF PR.AA | I11: Access control policy; latest access review | J11: Yes | K11: Yes | L11: Partial | M11: Partial | N11: Yes | O11: Partial
A12: IAM-03 | B12: Identity & Access Management | C12: Is privileged access tightly managed (separate admin accounts, PAM or just-in-time access, session logging)? | D12: All | E12: 2 | F12: No | G12: ISO 27001 A.8.2 | H12: CSF PR.AA | I12: PAM tooling evidence; privileged user list | J12: Yes | K12: Partial | L12: No | M12: Partial | N12: Yes | O12: No
A13: IAM-04 | B13: Identity & Access Management | C13: Does the joiner-mover-leaver process revoke access within 24 hours of termination? | D13: All | E13: 2 | F13: No | G13: ISO 27001 A.5.18, A.6.5 | H13: CSF PR.AA | I13: Offboarding procedure; sample tickets | J13: Yes | K13: Yes | L13: Partial | M13: Partial | N13: Yes | O13: Partial
A14: IAM-05 | B14: Identity & Access Management | C14: Does the service support SSO (SAML/OIDC), MFA and role-based access for customer users? | D14: All | E14: 1 | F14: No | G14: ISO 27001 A.5.16, A.8.5 | H14: CSF PR.AA | I14: Product documentation | J14: Yes | K14: Yes | L14: Partial | M14: Yes | N14: Yes | O14: Yes
A15: DAT-01 | B15: Data Protection & Privacy | C15: Is customer data encrypted at rest using industry-standard algorithms (e.g., AES-256)? | D15: All | E15: 3 | F15: Yes | G15: ISO 27001 A.8.24 | H15: CSF PR.DS | I15: Architecture document; encryption configuration | J15: Yes | K15: Yes | L15: Yes | M15: Yes | N15: Yes | O15: Yes
A16: DAT-02 | B16: Data Protection & Privacy | C16: Is customer data encrypted in transit using TLS 1.2 or higher? | D16: All | E16: 3 | F16: Yes | G16: ISO 27001 A.8.24, A.5.14 | H16: CSF PR.DS | I16: TLS configuration; external scan result | J16: Yes | K16: Yes | L16: Yes | M16: Yes | N16: Yes | O16: Yes
... A55: AIG-08 | B55: AI Governance & Model Risk | C55: Is there a defined process for AI incident reporting and customer notification (harmful outputs, model failure, data leakage), including alignment to applicable AI regulation (e.g., EU AI Act)? | D55: AI | E55: 2 | F55: No | G55: ISO 42001 Annex A.8.3, A.8.4 | H55: AI RMF MANAGE 4 | I55: AI incident procedure; regulatory mapping | J55: N/A | K55: No | L55: N/A | M55: No | N55: N/A | O55: N/A
A57: Mappings to ISO/IEC 27001:2022, ISO/IEC 42001:2023, NIST CSF 2.0 and NIST AI RMF 1.0 are indicative and should be validated against the current published standards before use in an audit.
A58: Mark AI-specific questions N/A for vendors without AI functionality. A 'No' on a Critical control is counted as a critical gap in Assessment_Results.

Sheet Assessment_Results
A1: Assessment Results – Control Effectiveness by Vendor
A2: Calculated from the Questionnaire. Domain scores = weighted share of controls implemented (Yes = 1, Partial = 0.5, No = 0; N/A excluded).
A5: Vendor ID | B5: Vendor name | C5: Overall control effectiveness | D5: Questionnaire completion | E5: Critical gaps | F5: Governance & Risk Management | G5: Identity & Access Management | H5: Data Protection & Privacy | I5: Cloud & Infrastructure Security | J5: Application & Vulnerability Management | K5: Logging, Monitoring & Incident Response | L5: Business Continuity & Resilience | M5: Subcontractor & Fourth-Party Management | N5: Legal, Regulatory & Compliance | O5: AI Governance & Model Risk
A6: =IF(Vendor_Register!A6="","",Vendor_Register!A6) -> V-001 | B6: =IF(A6="","",Vendor_Register!B6) -> Stratus Cloud Infrastructure | C6: =IF($A6="","",IFERROR(SUMPRODUCT(Questionnaire!$E$5:$E$55*((Questionnaire!J$5:J$55="Yes")*Methodology!$B$27+(Questionnaire!J$5:J$55="Partial")*Methodology!$B$28+(Questionnaire!J$5:J$55="No")*Methodology!$B$29))/SUMPRODUCT(Questionnaire!$E$5:$E$55*((Questionnaire!J$5:J$55="Yes")+(Questionnaire!J$5:J$55="Partial")+(Questionnaire!J$5:J$55="No"))),"")) -> 0.96153846 | D6: =IF($A6="","",SUMPRODUCT(--(Questionnaire!J$5:J$55<>""))/ROWS(Questionnaire!$A$5:$A$55)) -> 1 | E6: =IF($A6="","",SUMPRODUCT((Questionnaire!$F$5:$F$55="Yes")*(Questionnaire!J$5:J$55="No"))) -> 0 | F6: =IF($A6="","",IFERROR(SUMPRODUCT((Questionnaire!$B$5:$B$55=F$5)*Questionnaire!$E$5:$E$55*((Questionnaire!J$5:J$55="Yes")*Methodology!$B$27+(Questionnaire!J$5:J$55="Partial")*Methodology!$B$28+(Questionnaire!J$5:J$55="No")*Methodology!$B$29))/SUMPRODUCT((Questionnaire!$B$5:$B$55=F$5)*Questionnaire!$E$5:$E$55*((Questionnaire!J$5:J$55="Yes")+(Questionnaire!J$5:J$55="Partial")+(Questionnaire!J$5:J$55="No"))),"N/A")) -> 0.91666667 | G6: =IF($A6="","",IFERROR(SUMPRODUCT((Questionnaire!$B$5:$B$55=G$5)*Questionnaire!$E$5:$E$55*((Questionnaire!J$5:J$55="Yes")*Methodology!$B$27+(Questionnaire!J$5:J$55="Partial")*Methodology!$B$28+(Questionnaire!J$5:J$55="No")*Methodology!$B$29))/SUMPRODUCT((Questionnaire!$B$5:$B$55=G$5)*Questionnaire!$E$5:$E$55*((Questionnaire!J$5:J$55="Yes")+(Questionnaire!J$5:J$55="Partial")+(Questionnaire!J$5:J$55="No"))),"N/A")) -> 1 | H6: =IF($A6="","",IFERROR(SUMPRODUCT((Questionnaire!$B$5:$B$55=H$5)*Questionnaire!$E$5:$E$55*((Questionnaire!J$5:J$55="Yes")*Methodology!$B$27+(Questionnaire!J$5:J$55="Partial")*Methodology!$B$28+(Questionnaire!J$5:J$55="No")*Methodology!$B$29))/SUMPRODUCT((Questionnaire!$B$5:$B$55=H$5)*Questionnaire!$E$5:$E$55*((Questionnaire!J$5:J$55="Yes")+(Questionnaire!J$5:J$55="Partial")+(Questionnaire!J$5:J$55="No"))),"N/A")) -> 0.92857143 | I6: =IF($A6="","",IFERROR(SUMPRODUCT((Questionnaire!$B$5:$B$55=I$5)*Questionnaire!$E$5:$E$55*((Questionnaire!J$5:J$55="Yes")*Methodology!$B$27+(Questionnaire!J$5:J$55="Partial")*Methodology!$B$28+(Questionnaire!J$5:J$55="No")*Methodology!$B$29))/SUMPRODUCT((Questionnaire!$B$5:$B$55=I$5)*Questionnaire!$E$5:$E$55*((Questionnaire!J$5:J$55="Yes")+(Questionnaire!J$5:J$55="Partial")+(Questionnaire!J$5:J$55="No"))),"N/A")) -> 0.94444444 | J6: =IF($A6="","",IFERROR(SUMPRODUCT((Questionnaire!$B$5:$B$55=J$5)*Questionnaire!$E$5:$E$55*((Questionnaire!J$5:J$55="Yes")*Methodology!$B$27+(Questionnaire!J$5:J$55="Partial")*Methodology!$B$28+(Questionnaire!J$5:J$55="No")*Methodology!$B$29))/SUMPRODUCT((Questionnaire!$B$5:$B$55=J$5)*Questionnaire!$E$5:$E$55*((Questionnaire!J$5:J$55="Yes")+(Questionnaire!J$5:J$55="Partial")+(Questionnaire!J$5:J$55="No"))),"N/A")) -> 1 | K6: =IF($A6="","",IFERROR(SUMPRODUCT((Questionnaire!$B$5:$B$55=K$5)*Questionnaire!$E$5:$E$55*((Questionnaire!J$5:J$55="Yes")*Methodology!$B$27+(Questionnaire!J$5:J$55="Partial")*Methodology!$B$28+(Questionnaire!J$5:J$55="No")*Methodology!$B$29))/SUMPRODUCT((Questionnaire!$B$5:$B$55=K$5)*Questionnaire!$E$5:$E$55*((Questionnaire!J$5:J$55="Yes")+(Questionnaire!J$5:J$55="Partial")+(Questionnaire!J$5:J$55="No"))),"N/A")) -> 1 | L6: =IF($A6="","",IFERROR(SUMPRODUCT((Questionnaire!$B$5:$B$55=L$5)*Questionnaire!$E$5:$E$55*((Questionnaire!J$5:J$55="Yes")*Methodology!$B$27+(Questionnaire!J$5:J$55="Partial")*Methodology!$B$28+(Questionnaire!J$5:J$55="No")*Methodology!$B$29))/SUMPRODUCT((Questionnaire!$B$5:$B$55=L$5)*Questionnaire!$E$5:$E$55*((Questionnaire!J$5:J$55="Yes")+(Questionnaire!J$5:J$55="Partial")+(Questionnaire!J$5:J$55="No"))),"N/A")) -> 1 | M6: =IF($A6="","",IFERROR(SUMPRODUCT((Questionnaire!$B$5:$B$55=M$5)*Questionnaire!$E$5:$E$55*((Questionnaire!J$5:J$55="Yes")*Methodology!$B$27+(Questionnaire!J$5:J$55="Partial")*Methodology!$B$28+(Questionnaire!J$5:J$55="No")*Methodology!$B$29))/SUMPRODUCT((Questionnaire!$B$5:$B$55=M$5)*Questionnaire!$E$5:$E$55*((Questionnaire!J$5:J$55="Yes")+(Questionnaire!J$5:J$55="Partial")+(Questionnaire!J$5:J$55="No"))),"N/A")) -> 0.85714286 | N6: =IF($A6="","",IFERROR(SUMPRODUCT((Questionnaire!$B$5:$B$55=N$5)*Questionnaire!$E$5:$E$55*((Questionnaire!J$5:J$55="Yes")*Methodology!$B$27+(Questionnaire!J$5:J$55="Partial")*Methodology!$B$28+(Questionnaire!J$5:J$55="No")*Methodology!$B$29))/SUMPRODUCT((Questionnaire!$B$5:$B$55=N$5)*Questionnaire!$E$5:$E$55*((Questionnaire!J$5:J$55="Yes")+(Questionnaire!J$5:J$55="Partial")+(Questionnaire!J$5:J$55="No"))),"N/A")) -> 1 | O6: =IF($A6="","",IFERROR(SUMPRODUCT((Questionnaire!$B$5:$B$55=O$5)*Questionnaire!$E$5:$E$55*((Questionnaire!J$5:J$55="Yes")*Methodology!$B$27+(Questionnaire!J$5:J$55="Partial")*Methodology!$B$28+(Questionnaire!J$5:J$55="No")*Methodology!$B$29))/SUMPRODUCT((Questionnaire!$B$5:$B$55=O$5)*Questionnaire!$E$5:$E$55*((Questionnaire!J$5:J$55="Yes")+(Questionnaire!J$5:J$55="Partial")+(Questionnaire!J$5:J$55="No"))),"N/A")) -> N/A
A7: =IF(Vendor_Register!A7="","",Vendor_Register!A7) -> V-002 | B7: =IF(A7="","",Vendor_Register!B7) -> NimbusAI Language Platform | C7: =IF($A7="","",IFERROR(SUMPRODUCT(Questionnaire!$E$5:$E$55*((Questionnaire!K$5:K$55="Yes")*Methodology!$B$27+(Questionnaire!K$5:K$55="Partial")*Methodology!$B$28+(Questionnaire!K$5:K$55="No")*Methodology!$B$29))/SUMPRODUCT(Questionnaire!$E$5:$E$55*((Questionnaire!K$5:K$55="Yes")+(Questionnaire!K$5:K$55="Partial")+(Questionnaire!K$5:K$55="No"))),"")) -> 0.81531532 | D7: =IF($A7="","",SUMPRODUCT(--(Questionnaire!K$5:K$55<>""))/ROWS(Questionnaire!$A$5:$A$55)) -> 1 | E7: =IF($A7="","",SUMPRODUCT((Questionnaire!$F$5:$F$55="Yes")*(Questionnaire!K$5:K$55="No"))) -> 1 | F7: =IF($A7="","",IFERROR(SUMPRODUCT((Questionnaire!$B$5:$B$55=F$5)*Questionnaire!$E$5:$E$55*((Questionnaire!K$5:K$55="Yes")*Methodology!$B$27+(Questionnaire!K$5:K$55="Partial")*Methodology!$B$28+(Questionnaire!K$5:K$55="No")*Methodology!$B$29))/SUMPRODUCT((Questionnaire!$B$5:$B$55=F$5)*Questionnaire!$E$5:$E$55*((Questionnaire!K$5:K$55="Yes")+(Questionnaire!K$5:K$55="Partial")+(Questionnaire!K$5:K$55="No"))),"N/A")) -> 0.875 | G7: =IF($A7="","",IFERROR(SUMPRODUCT((Questionnaire!$B$5:$B$55=G$5)*Questionnaire!$E$5:$E$55*((Questionnaire!K$5:K$55="Yes")*Methodology!$B$27+(Questionnaire!K$5:K$55="Partial")*Methodology!$B$28+(Questionnaire!K$5:K$55="No")*Methodology!$B$29))/SUMPRODUCT((Questionnaire!$B$5:$B$55=G$5)*Questionnaire!$E$5:$E$55*((Questionnaire!K$5:K$55="Yes")+(Questionnaire!K$5:K$55="Partial")+(Questionnaire!K$5:K$55="No"))),"N/A")) -> 0.9 | H7: =IF($A7="","",IFERROR(SUMPRODUCT((Questionnaire!$B$5:$B$55=H$5)*Questionnaire!$E$5:$E$55*((Questionnaire!K$5:K$55="Yes")*Methodology!$B$27+(Questionnaire!K$5:K$55="Partial")*Methodology!$B$28+(Questionnaire!K$5:K$55="No")*Methodology!$B$29))/SUMPRODUCT((Questionnaire!$B$5:$B$55=H$5)*Questionnaire!$E$5:$E$55*((Questionnaire!K$5:K$55="Yes")+(Questionnaire!K$5:K$55="Partial")+(Questionnaire!K$5:K$55="No"))),"N/A")) -> 0.92857143 | I7: =IF($A7="","",IFERROR(SUMPRODUCT((Questionnaire!$B$5:$B$55=I$5)*Questionnaire!$E$5:$E$55*((Questionnaire!K$5:K$55="Yes")*Methodology!$B$27+(Questionnaire!K$5:K$55="Partial")*Methodology!$B$28+(Questionnaire!K$5:K$55="No")*Methodology!$B$29))/SUMPRODUCT((Questionnaire!$B$5:$B$55=I$5)*Questionnaire!$E$5:$E$55*((Questionnaire!K$5:K$55="Yes")+(Questionnaire!K$5:K$55="Partial")+(Questionnaire!K$5:K$55="No"))),"N/A")) -> 1 | J7: =IF($A7="","",IFERROR(SUMPRODUCT((Questionnaire!$B$5:$B$55=J$5)*Questionnaire!$E$5:$E$55*((Questionnaire!K$5:K$55="Yes")*Methodology!$B$27+(Questionnaire!K$5:K$55="Partial")*Methodology!$B$28+(Questionnaire!K$5:K$55="No")*Methodology!$B$29))/SUMPRODUCT((Questionnaire!$B$5:$B$55=J$5)*Questionnaire!$E$5:$E$55*((Questionnaire!K$5:K$55="Yes")+(Questionnaire!K$5:K$55="Partial")+(Questionnaire!K$5:K$55="No"))),"N/A")) -> 0.875 | K7: =IF($A7="","",IFERROR(SUMPRODUCT((Questionnaire!$B$5:$B$55=K$5)*Questionnaire!$E$5:$E$55*((Questionnaire!K$5:K$55="Yes")*Methodology!$B$27+(Questionnaire!K$5:K$55="Partial")*Methodology!$B$28+(Questionnaire!K$5:K$55="No")*Methodology!$B$29))/SUMPRODUCT((Questionnaire!$B$5:$B$55=K$5)*Questionnaire!$E$5:$E$55*((Questionnaire!K$5:K$55="Yes")+(Questionnaire!K$5:K$55="Partial")+(Questionnaire!K$5:K$55="No"))),"N/A")) -> 0.86363636 | L7: =IF($A7="","",IFERROR(SUMPRODUCT((Questionnaire!$B$5:$B$55=L$5)*Questionnaire!$E$5:$E$55*((Questionnaire!K$5:K$55="Yes")*Methodology!$B$27+(Questionnaire!K$5:K$55="Partial")*Methodology!$B$28+(Questionnaire!K$5:K$55="No")*Methodology!$B$29))/SUMPRODUCT((Questionnaire!$B$5:$B$55=L$5)*Questionnaire!$E$5:$E$55*((Questionnaire!K$5:K$55="Yes")+(Questionnaire!K$5:K$55="Partial")+(Questionnaire!K$5:K$55="No"))),"N/A")) -> 0.875 | M7: =IF($A7="","",IFERROR(SUMPRODUCT((Questionnaire!$B$5:$B$55=M$5)*Questionnaire!$E$5:$E$55*((Questionnaire!K$5:K$55="Yes")*Methodology!$B$27+(Questionnaire!K$5:K$55="Partial")*Methodology!$B$28+(Questionnaire!K$5:K$55="No")*Methodology!$B$29))/SUMPRODUCT((Questionnaire!$B$5:$B$55=M$5)*Questionnaire!$E$5:$E$55*((Questionnaire!K$5:K$55="Yes")+(Questionnaire!K$5:K$55="Partial")+(Questionnaire!K$5:K$55="No"))),"N/A")) -> 0.78571429 | N7: =IF($A7="","",IFERROR(SUMPRODUCT((Questionnaire!$B$5:$B$55=N$5)*Questionnaire!$E$5:$E$55*((Questionnaire!K$5:K$55="Yes")*Methodology!$B$27+(Questionnaire!K$5:K$55="Partial")*Methodology!$B$28+(Questionnaire!K$5:K$55="No")*Methodology!$B$29))/SUMPRODUCT((Questionnaire!$B$5:$B$55=N$5)*Questionnaire!$E$5:$E$55*((Questionnaire!K$5:K$55="Yes")+(Questionnaire!K$5:K$55="Partial")+(Questionnaire!K$5:K$55="No"))),"N/A")) -> 0.875 | O7: =IF($A7="","",IFERROR(SUMPRODUCT((Questionnaire!$B$5:$B$55=O$5)*Questionnaire!$E$5:$E$55*((Questionnaire!K$5:K$55="Yes")*Methodology!$B$27+(Questionnaire!K$5:K$55="Partial")*Methodology!$B$28+(Questionnaire!K$5:K$55="No")*Methodology!$B$29))/SUMPRODUCT((Questionnaire!$B$5:$B$55=O$5)*Questionnaire!$E$5:$E$55*((Questionnaire!K$5:K$55="Yes")+(Questionnaire!K$5:K$55="Partial")+(Questionnaire!K$5:K$55="No"))),"N/A")) -> 0.475
A8: =IF(Vendor_Register!A8="","",Vendor_Register!A8) -> V-003 | B8: =IF(A8="","",Vendor_Register!B8) -> Orbit CRM Suite | C8: =IF($A8="","",IFERROR(SUMPRODUCT(Questionnaire!$E$5:$E$55*((Questionnaire!L$5:L$55="Yes")*Methodology!$B$27+(Questionnaire!L$5:L$55="Partial")*Methodology!$B$28+(Questionnaire!L$5:L$55="No")*Methodology!$B$29))/SUMPRODUCT(Questionnaire!$E$5:$E$55*((Questionnaire!L$5:L$55="Yes")+(Questionnaire!L$5:L$55="Partial")+(Questionnaire!L$5:L$55="No"))),"")) -> 0.51098901 | D8: =IF($A8="","",SUMPRODUCT(--(Questionnaire!L$5:L$55<>""))/ROWS(Questionnaire!$A$5:$A$55)) -> 1 | E8: =IF($A8="","",SUMPRODUCT((Questionnaire!$F$5:$F$55="Yes")*(Questionnaire!L$5:L$55="No"))) -> 0 | F8: =IF($A8="","",IFERROR(SUMPRODUCT((Questionnaire!$B$5:$B$55=F$5)*Questionnaire!$E$5:$E$55*((Questionnaire!L$5:L$55="Yes")*Methodology!$B$27+(Questionnaire!L$5:L$55="Partial")*Methodology!$B$28+(Questionnaire!L$5:L$55="No")*Methodology!$B$29))/SUMPRODUCT((Questionnaire!$B$5:$B$55=F$5)*Questionnaire!$E$5:$E$55*((Questionnaire!L$5:L$55="Yes")+(Questionnaire!L$5:L$55="Partial")+(Questionnaire!L$5:L$55="No"))),"N/A")) -> 0.54166667 | G8: =IF($A8="","",IFERROR(SUMPRODUCT((Questionnaire!$B$5:$B$55=G$5)*Questionnaire!$E$5:$E$55*((Questionnaire!L$5:L$55="Yes")*Methodology!$B$27+(Questionnaire!L$5:L$55="Partial")*Methodology!$B$28+(Questionnaire!L$5:L$55="No")*Methodology!$B$29))/SUMPRODUCT((Questionnaire!$B$5:$B$55=G$5)*Questionnaire!$E$5:$E$55*((Questionnaire!L$5:L$55="Yes")+(Questionnaire!L$5:L$55="Partial")+(Questionnaire!L$5:L$55="No"))),"N/A")) -> 0.55 | H8: =IF($A8="","",IFERROR(SUMPRODUCT((Questionnaire!$B$5:$B$55=H$5)*Questionnaire!$E$5:$E$55*((Questionnaire!L$5:L$55="Yes")*Methodology!$B$27+(Questionnaire!L$5:L$55="Partial")*Methodology!$B$28+(Questionnaire!L$5:L$55="No")*Methodology!$B$29))/SUMPRODUCT((Questionnaire!$B$5:$B$55=H$5)*Questionnaire!$E$5:$E$55*((Questionnaire!L$5:L$55="Yes")+(Questionnaire!L$5:L$55="Partial")+(Questionnaire!L$5:L$55="No"))),"N/A")) -> 0.57142857 | I8: =IF($A8="","",IFERROR(SUMPRODUCT((Questionnaire!$B$5:$B$55=I$5)*Questionnaire!$E$5:$E$55*((Questionnaire!L$5:L$55="Yes")*Methodology!$B$27+(Questionnaire!L$5:L$55="Partial")*Methodology!$B$28+(Questionnaire!L$5:L$55="No")*Methodology!$B$29))/SUMPRODUCT((Questionnaire!$B$5:$B$55=I$5)*Questionnaire!$E$5:$E$55*((Questionnaire!L$5:L$55="Yes")+(Questionnaire!L$5:L$55="Partial")+(Questionnaire!L$5:L$55="No"))),"N/A")) -> 0.66666667 | J8: =IF($A8="","",IFERROR(SUMPRODUCT((Questionnaire!$B$5:$B$55=J$5)*Questionnaire!$E$5:$E$55*((Questionnaire!L$5:L$55="Yes")*Methodology!$B$27+(Questionnaire!L$5:L$55="Partial")*Methodology!$B$28+(Questionnaire!L$5:L$55="No")*Methodology!$B$29))/SUMPRODUCT((Questionnaire!$B$5:$B$55=J$5)*Questionnaire!$E$5:$E$55*((Questionnaire!L$5:L$55="Yes")+(Questionnaire!L$5:L$55="Partial")+(Questionnaire!L$5:L$55="No"))),"N/A")) -> 0.29166667 | K8: =IF($A8="","",IFERROR(SUMPRODUCT((Questionnaire!$B$5:$B$55=K$5)*Questionnaire!$E$5:$E$55*((Questionnaire!L$5:L$55="Yes")*Methodology!$B$27+(Questionnaire!L$5:L$55="Partial")*Methodology!$B$28+(Questionnaire!L$5:L$55="No")*Methodology!$B$29))/SUMPRODUCT((Questionnaire!$B$5:$B$55=K$5)*Questionnaire!$E$5:$E$55*((Questionnaire!L$5:L$55="Yes")+(Questionnaire!L$5:L$55="Partial")+(Questionnaire!L$5:L$55="No"))),"N/A")) -> 0.45454545 | L8: =IF($A8="","",IFERROR(SUMPRODUCT((Questionnaire!$B$5:$B$55=L$5)*Questionnaire!$E$5:$E$55*((Questionnaire!L$5:L$55="Yes")*Methodology!$B$27+(Questionnaire!L$5:L$55="Partial")*Methodology!$B$28+(Questionnaire!L$5:L$55="No")*Methodology!$B$29))/SUMPRODUCT((Questionnaire!$B$5:$B$55=L$5)*Questionnaire!$E$5:$E$55*((Questionnaire!L$5:L$55="Yes")+(Questionnaire!L$5:L$55="Partial")+(Questionnaire!L$5:L$55="No"))),"N/A")) -> 0.375 | M8: =IF($A8="","",IFERROR(SUMPRODUCT((Questionnaire!$B$5:$B$55=M$5)*Questionnaire!$E$5:$E$55*((Questionnaire!L$5:L$55="Yes")*Methodology!$B$27+(Questionnaire!L$5:L$55="Partial")*Methodology!$B$28+(Questionnaire!L$5:L$55="No")*Methodology!$B$29))/SUMPRODUCT((Questionnaire!$B$5:$B$55=M$5)*Questionnaire!$E$5:$E$55*((Questionnaire!L$5:L$55="Yes")+(Questionnaire!L$5:L$55="Partial")+(Questionnaire!L$5:L$55="No"))),"N/A")) -> 0.42857143 | N8: =IF($A8="","",IFERROR(SUMPRODUCT((Questionnaire!$B$5:$B$55=N$5)*Questionnaire!$E$5:$E$55*((Questionnaire!L$5:L$55="Yes")*Methodology!$B$27+(Questionnaire!L$5:L$55="Partial")*Methodology!$B$28+(Questionnaire!L$5:L$55="No")*Methodology!$B$29))/SUMPRODUCT((Questionnaire!$B$5:$B$55=N$5)*Questionnaire!$E$5:$E$55*((Questionnaire!L$5:L$55="Yes")+(Questionnaire!L$5:L$55="Partial")+(Questionnaire!L$5:L$55="No"))),"N/A")) -> 0.75 | O8: =IF($A8="","",IFERROR(SUMPRODUCT((Questionnaire!$B$5:$B$55=O$5)*Questionnaire!$E$5:$E$55*((Questionnaire!L$5:L$55="Yes")*Methodology!$B$27+(Questionnaire!L$5:L$55="Partial")*Methodology!$B$28+(Questionnaire!L$5:L$55="No")*Methodology!$B$29))/SUMPRODUCT((Questionnaire!$B$5:$B$55=O$5)*Questionnaire!$E$5:$E$55*((Questionnaire!L$5:L$55="Yes")+(Questionnaire!L$5:L$55="Partial")+(Questionnaire!L$5:L$55="No"))),"N/A")) -> N/A
A9: =IF(Vendor_Register!A9="","",Vendor_Register!A9) -> V-004 | B9: =IF(A9="","",Vendor_Register!B9) -> InsightML Analytics | C9: =IF($A9="","",IFERROR(SUMPRODUCT(Questionnaire!$E$5:$E$55*((Questionnaire!M$5:M$55="Yes")*Methodology!$B$27+(Questionnaire!M$5:M$55="Partial")*Methodology!$B$28+(Questionnaire!M$5:M$55="No")*Methodology!$B$29))/SUMPRODUCT(Questionnaire!$E$5:$E$55*((Questionnaire!M$5:M$55="Yes")+(Questionnaire!M$5:M$55="Partial")+(Questionnaire!M$5:M$55="No"))),"")) -> 0.74324324 | D9: =IF($A9="","",SUMPRODUCT(--(Questionnaire!M$5:M$55<>""))/ROWS(Questionnaire!$A$5:$A$55)) -> 1 | E9: =IF($A9="","",SUMPRODUCT((Questionnaire!$F$5:$F$55="Yes")*(Questionnaire!M$5:M$55="No"))) -> 0 | F9: =IF($A9="","",IFERROR(SUMPRODUCT((Questionnaire!$B$5:$B$55=F$5)*Questionnaire!$E$5:$E$55*((Questionnaire!M$5:M$55="Yes")*Methodology!$B$27+(Questionnaire!M$5:M$55="Partial")*Methodology!$B$28+(Questionnaire!M$5:M$55="No")*Methodology!$B$29))/SUMPRODUCT((Questionnaire!$B$5:$B$55=F$5)*Questionnaire!$E$5:$E$55*((Questionnaire!M$5:M$55="Yes")+(Questionnaire!M$5:M$55="Partial")+(Questionnaire!M$5:M$55="No"))),"N/A")) -> 0.70833333 | G9: =IF($A9="","",IFERROR(SUMPRODUCT((Questionnaire!$B$5:$B$55=G$5)*Questionnaire!$E$5:$E$55*((Questionnaire!M$5:M$55="Yes")*Methodology!$B$27+(Questionnaire!M$5:M$55="Partial")*Methodology!$B$28+(Questionnaire!M$5:M$55="No")*Methodology!$B$29))/SUMPRODUCT((Questionnaire!$B$5:$B$55=G$5)*Questionnaire!$E$5:$E$55*((Questionnaire!M$5:M$55="Yes")+(Questionnaire!M$5:M$55="Partial")+(Questionnaire!M$5:M$55="No"))),"N/A")) -> 0.7 | H9: =IF($A9="","",IFERROR(SUMPRODUCT((Questionnaire!$B$5:$B$55=H$5)*Questionnaire!$E$5:$E$55*((Questionnaire!M$5:M$55="Yes")*Methodology!$B$27+(Questionnaire!M$5:M$55="Partial")*Methodology!$B$28+(Questionnaire!M$5:M$55="No")*Methodology!$B$29))/SUMPRODUCT((Questionnaire!$B$5:$B$55=H$5)*Questionnaire!$E$5:$E$55*((Questionnaire!M$5:M$55="Yes")+(Questionnaire!M$5:M$55="Partial")+(Questionnaire!M$5:M$55="No"))),"N/A")) -> 0.85714286 | I9: =IF($A9="","",IFERROR(SUMPRODUCT((Questionnaire!$B$5:$B$55=I$5)*Questionnaire!$E$5:$E$55*((Questionnaire!M$5:M$55="Yes")*Methodology!$B$27+(Questionnaire!M$5:M$55="Partial")*Methodology!$B$28+(Questionnaire!M$5:M$55="No")*Methodology!$B$29))/SUMPRODUCT((Questionnaire!$B$5:$B$55=I$5)*Questionnaire!$E$5:$E$55*((Questionnaire!M$5:M$55="Yes")+(Questionnaire!M$5:M$55="Partial")+(Questionnaire!M$5:M$55="No"))),"N/A")) -> 0.77777778 | J9: =IF($A9="","",IFERROR(SUMPRODUCT((Questionnaire!$B$5:$B$55=J$5)*Questionnaire!$E$5:$E$55*((Questionnaire!M$5:M$55="Yes")*Methodology!$B$27+(Questionnaire!M$5:M$55="Partial")*Methodology!$B$28+(Questionnaire!M$5:M$55="No")*Methodology!$B$29))/SUMPRODUCT((Questionnaire!$B$5:$B$55=J$5)*Questionnaire!$E$5:$E$55*((Questionnaire!M$5:M$55="Yes")+(Questionnaire!M$5:M$55="Partial")+(Questionnaire!M$5:M$55="No"))),"N/A")) -> 0.75 | K9: =IF($A9="","",IFERROR(SUMPRODUCT((Questionnaire!$B$5:$B$55=K$5)*Questionnaire!$E$5:$E$55*((Questionnaire!M$5:M$55="Yes")*Methodology!$B$27+(Questionnaire!M$5:M$55="Partial")*Methodology!$B$28+(Questionnaire!M$5:M$55="No")*Methodology!$B$29))/SUMPRODUCT((Questionnaire!$B$5:$B$55=K$5)*Questionnaire!$E$5:$E$55*((Questionnaire!M$5:M$55="Yes")+(Questionnaire!M$5:M$55="Partial")+(Questionnaire!M$5:M$55="No"))),"N/A")) -> 0.86363636 | L9: =IF($A9="","",IFERROR(SUMPRODUCT((Questionnaire!$B$5:$B$55=L$5)*Questionnaire!$E$5:$E$55*((Questionnaire!M$5:M$55="Yes")*Methodology!$B$27+(Questionnaire!M$5:M$55="Partial")*Methodology!$B$28+(Questionnaire!M$5:M$55="No")*Methodology!$B$29))/SUMPRODUCT((Questionnaire!$B$5:$B$55=L$5)*Questionnaire!$E$5:$E$55*((Questionnaire!M$5:M$55="Yes")+(Questionnaire!M$5:M$55="Partial")+(Questionnaire!M$5:M$55="No"))),"N/A")) -> 0.625 | M9: =IF($A9="","",IFERROR(SUMPRODUCT((Questionnaire!$B$5:$B$55=M$5)*Questionnaire!$E$5:$E$55*((Questionnaire!M$5:M$55="Yes")*Methodology!$B$27+(Questionnaire!M$5:M$55="Partial")*Methodology!$B$28+(Questionnaire!M$5:M$55="No")*Methodology!$B$29))/SUMPRODUCT((Questionnaire!$B$5:$B$55=M$5)*Questionnaire!$E$5:$E$55*((Questionnaire!M$5:M$55="Yes")+(Questionnaire!M$5:M$55="Partial")+(Questionnaire!M$5:M$55="No"))),"N/A")) -> 0.78571429 | N9: =IF($A9="","",IFERROR(SUMPRODUCT((Questionnaire!$B$5:$B$55=N$5)*Questionnaire!$E$5:$E$55*((Questionnaire!M$5:M$55="Yes")*Methodology!$B$27+(Questionnaire!M$5:M$55="Partial")*Methodology!$B$28+(Questionnaire!M$5:M$55="No")*Methodology!$B$29))/SUMPRODUCT((Questionnaire!$B$5:$B$55=N$5)*Questionnaire!$E$5:$E$55*((Questionnaire!M$5:M$55="Yes")+(Questionnaire!M$5:M$55="Partial")+(Questionnaire!M$5:M$55="No"))),"N/A")) -> 0.75 | O9: =IF($A9="","",IFERROR(SUMPRODUCT((Questionnaire!$B$5:$B$55=O$5)*Questionnaire!$E$5:$E$55*((Questionnaire!M$5:M$55="Yes")*Methodology!$B$27+(Questionnaire!M$5:M$55="Partial")*Methodology!$B$28+(Questionnaire!M$5:M$55="No")*Methodology!$B$29))/SUMPRODUCT((Questionnaire!$B$5:$B$55=O$5)*Questionnaire!$E$5:$E$55*((Questionnaire!M$5:M$55="Yes")+(Questionnaire!M$5:M$55="Partial")+(Questionnaire!M$5:M$55="No"))),"N/A")) -> 0.65
A10: =IF(Vendor_Register!A10="","",Vendor_Register!A10) -> V-005 | B10: =IF(A10="","",Vendor_Register!B10) -> Cirrus Backup & Recovery | C10: =IF($A10="","",IFERROR(SUMPRODUCT(Questionnaire!$E$5:$E$55*((Questionnaire!N$5:N$55="Yes")*Methodology!$B$27+(Questionnaire!N$5:N$55="Partial")*Methodology!$B$28+(Questionnaire!N$5:N$55="No")*Methodology!$B$29))/SUMPRODUCT(Questionnaire!$E$5:$E$55*((Questionnaire!N$5:N$55="Yes")+(Questionnaire!N$5:N$55="Partial")+(Questionnaire!N$5:N$55="No"))),"")) -> 0.95604396 | D10: =IF($A10="","",SUMPRODUCT(--(Questionnaire!N$5:N$55<>""))/ROWS(Questionnaire!$A$5:$A$55)) -> 1 | E10: =IF($A10="","",SUMPRODUCT((Questionnaire!$F$5:$F$55="Yes")*(Questionnaire!N$5:N$55="No"))) -> 0 | F10: =IF($A10="","",IFERROR(SUMPRODUCT((Questionnaire!$B$5:$B$55=F$5)*Questionnaire!$E$5:$E$55*((Questionnaire!N$5:N$55="Yes")*Methodology!$B$27+(Questionnaire!N$5:N$55="Partial")*Methodology!$B$28+(Questionnaire!N$5:N$55="No")*Methodology!$B$29))/SUMPRODUCT((Questionnaire!$B$5:$B$55=F$5)*Questionnaire!$E$5:$E$55*((Questionnaire!N$5:N$55="Yes")+(Questionnaire!N$5:N$55="Partial")+(Questionnaire!N$5:N$55="No"))),"N/A")) -> 0.91666667 | G10: =IF($A10="","",IFERROR(SUMPRODUCT((Questionnaire!$B$5:$B$55=G$5)*Questionnaire!$E$5:$E$55*((Questionnaire!N$5:N$55="Yes")*Methodology!$B$27+(Questionnaire!N$5:N$55="Partial")*Methodology!$B$28+(Questionnaire!N$5:N$55="No")*Methodology!$B$29))/SUMPRODUCT((Questionnaire!$B$5:$B$55=G$5)*Questionnaire!$E$5:$E$55*((Questionnaire!N$5:N$55="Yes")+(Questionnaire!N$5:N$55="Partial")+(Questionnaire!N$5:N$55="No"))),"N/A")) -> 1 | H10: =IF($A10="","",IFERROR(SUMPRODUCT((Questionnaire!$B$5:$B$55=H$5)*Questionnaire!$E$5:$E$55*((Questionnaire!N$5:N$55="Yes")*Methodology!$B$27+(Questionnaire!N$5:N$55="Partial")*Methodology!$B$28+(Questionnaire!N$5:N$55="No")*Methodology!$B$29))/SUMPRODUCT((Questionnaire!$B$5:$B$55=H$5)*Questionnaire!$E$5:$E$55*((Questionnaire!N$5:N$55="Yes")+(Questionnaire!N$5:N$55="Partial")+(Questionnaire!N$5:N$55="No"))),"N/A")) -> 0.92857143 | I10: =IF($A10="","",IFERROR(SUMPRODUCT((Questionnaire!$B$5:$B$55=I$5)*Questionnaire!$E$5:$E$55*((Questionnaire!N$5:N$55="Yes")*Methodology!$B$27+(Questionnaire!N$5:N$55="Partial")*Methodology!$B$28+(Questionnaire!N$5:N$55="No")*Methodology!$B$29))/SUMPRODUCT((Questionnaire!$B$5:$B$55=I$5)*Questionnaire!$E$5:$E$55*((Questionnaire!N$5:N$55="Yes")+(Questionnaire!N$5:N$55="Partial")+(Questionnaire!N$5:N$55="No"))),"N/A")) -> 0.94444444 | J10: =IF($A10="","",IFERROR(SUMPRODUCT((Questionnaire!$B$5:$B$55=J$5)*Questionnaire!$E$5:$E$55*((Questionnaire!N$5:N$55="Yes")*Methodology!$B$27+(Questionnaire!N$5:N$55="Partial")*Methodology!$B$28+(Questionnaire!N$5:N$55="No")*Methodology!$B$29))/SUMPRODUCT((Questionnaire!$B$5:$B$55=J$5)*Questionnaire!$E$5:$E$55*((Questionnaire!N$5:N$55="Yes")+(Questionnaire!N$5:N$55="Partial")+(Questionnaire!N$5:N$55="No"))),"N/A")) -> 1 | K10: =IF($A10="","",IFERROR(SUMPRODUCT((Questionnaire!$B$5:$B$55=K$5)*Questionnaire!$E$5:$E$55*((Questionnaire!N$5:N$55="Yes")*Methodology!$B$27+(Questionnaire!N$5:N$55="Partial")*Methodology!$B$28+(Questionnaire!N$5:N$55="No")*Methodology!$B$29))/SUMPRODUCT((Questionnaire!$B$5:$B$55=K$5)*Questionnaire!$E$5:$E$55*((Questionnaire!N$5:N$55="Yes")+(Questionnaire!N$5:N$55="Partial")+(Questionnaire!N$5:N$55="No"))),"N/A")) -> 0.95454545 | L10: =IF($A10="","",IFERROR(SUMPRODUCT((Questionnaire!$B$5:$B$55=L$5)*Questionnaire!$E$5:$E$55*((Questionnaire!N$5:N$55="Yes")*Methodology!$B$27+(Questionnaire!N$5:N$55="Partial")*Methodology!$B$28+(Questionnaire!N$5:N$55="No")*Methodology!$B$29))/SUMPRODUCT((Questionnaire!$B$5:$B$55=L$5)*Questionnaire!$E$5:$E$55*((Questionnaire!N$5:N$55="Yes")+(Questionnaire!N$5:N$55="Partial")+(Questionnaire!N$5:N$55="No"))),"N/A")) -> 1 | M10: =IF($A10="","",IFERROR(SUMPRODUCT((Questionnaire!$B$5:$B$55=M$5)*Questionnaire!$E$5:$E$55*((Questionnaire!N$5:N$55="Yes")*Methodology!$B$27+(Questionnaire!N$5:N$55="Partial")*Methodology!$B$28+(Questionnaire!N$5:N$55="No")*Methodology!$B$29))/SUMPRODUCT((Questionnaire!$B$5:$B$55=M$5)*Questionnaire!$E$5:$E$55*((Questionnaire!N$5:N$55="Yes")+(Questionnaire!N$5:N$55="Partial")+(Questionnaire!N$5:N$55="No"))),"N/A")) -> 0.92857143 | N10: =IF($A10="","",IFERROR(SUMPRODUCT((Questionnaire!$B$5:$B$55=N$5)*Questionnaire!$E$5:$E$55*((Questionnaire!N$5:N$55="Yes")*Methodology!$B$27+(Questionnaire!N$5:N$55="Partial")*Methodology!$B$28+(Questionnaire!N$5:N$55="No")*Methodology!$B$29))/SUMPRODUCT((Questionnaire!$B$5:$B$55=N$5)*Questionnaire!$E$5:$E$55*((Questionnaire!N$5:N$55="Yes")+(Questionnaire!N$5:N$55="Partial")+(Questionnaire!N$5:N$55="No"))),"N/A")) -> 0.9375 | O10: =IF($A10="","",IFERROR(SUMPRODUCT((Questionnaire!$B$5:$B$55=O$5)*Questionnaire!$E$5:$E$55*((Questionnaire!N$5:N$55="Yes")*Methodology!$B$27+(Questionnaire!N$5:N$55="Partial")*Methodology!$B$28+(Questionnaire!N$5:N$55="No")*Methodology!$B$29))/SUMPRODUCT((Questionnaire!$B$5:$B$55=O$5)*Questionnaire!$E$5:$E$55*((Questionnaire!N$5:N$55="Yes")+(Questionnaire!N$5:N$55="Partial")+(Questionnaire!N$5:N$55="No"))),"N/A")) -> N/A
A11: =IF(Vendor_Register!A11="","",Vendor_Register!A11) -> V-006 | B11: =IF(A11="","",Vendor_Register!B11) -> Brightleaf Survey Tool | C11: =IF($A11="","",IFERROR(SUMPRODUCT(Questionnaire!$E$5:$E$55*((Questionnaire!O$5:O$55="Yes")*Methodology!$B$27+(Questionnaire!O$5:O$55="Partial")*Methodology!$B$28+(Questionnaire!O$5:O$55="No")*Methodology!$B$29))/SUMPRODUCT(Questionnaire!$E$5:$E$55*((Questionnaire!O$5:O$55="Yes")+(Questionnaire!O$5:O$55="Partial")+(Questionnaire!O$5:O$55="No"))),"")) -> 0.58791209 | D11: =IF($A11="","",SUMPRODUCT(--(Questionnaire!O$5:O$55<>""))/ROWS(Questionnaire!$A$5:$A$55)) -> 1 | E11: =IF($A11="","",SUMPRODUCT((Questionnaire!$F$5:$F$55="Yes")*(Questionnaire!O$5:O$55="No"))) -> 0 | F11: =IF($A11="","",IFERROR(SUMPRODUCT((Questionnaire!$B$5:$B$55=F$5)*Questionnaire!$E$5:$E$55*((Questionnaire!O$5:O$55="Yes")*Methodology!$B$27+(Questionnaire!O$5:O$55="Partial")*Methodology!$B$28+(Questionnaire!O$5:O$55="No")*Methodology!$B$29))/SUMPRODUCT((Questionnaire!$B$5:$B$55=F$5)*Questionnaire!$E$5:$E$55*((Questionnaire!O$5:O$55="Yes")+(Questionnaire!O$5:O$55="Partial")+(Questionnaire!O$5:O$55="No"))),"N/A")) -> 0.41666667 | G11: =IF($A11="","",IFERROR(SUMPRODUCT((Questionnaire!$B$5:$B$55=G$5)*Questionnaire!$E$5:$E$55*((Questionnaire!O$5:O$55="Yes")*Methodology!$B$27+(Questionnaire!O$5:O$55="Partial")*Methodology!$B$28+(Questionnaire!O$5:O$55="No")*Methodology!$B$29))/SUMPRODUCT((Questionnaire!$B$5:$B$55=G$5)*Questionnaire!$E$5:$E$55*((Questionnaire!O$5:O$55="Yes")+(Questionnaire!O$5:O$55="Partial")+(Questionnaire!O$5:O$55="No"))),"N/A")) -> 0.6 | H11: =IF($A11="","",IFERROR(SUMPRODUCT((Questionnaire!$B$5:$B$55=H$5)*Questionnaire!$E$5:$E$55*((Questionnaire!O$5:O$55="Yes")*Methodology!$B$27+(Questionnaire!O$5:O$55="Partial")*Methodology!$B$28+(Questionnaire!O$5:O$55="No")*Methodology!$B$29))/SUMPRODUCT((Questionnaire!$B$5:$B$55=H$5)*Questionnaire!$E$5:$E$55*((Questionnaire!O$5:O$55="Yes")+(Questionnaire!O$5:O$55="Partial")+(Questionnaire!O$5:O$55="No"))),"N/A")) -> 0.71428571 | I11: =IF($A11="","",IFERROR(SUMPRODUCT((Questionnaire!$B$5:$B$55=I$5)*Questionnaire!$E$5:$E$55*((Questionnaire!O$5:O$55="Yes")*Methodology!$B$27+(Questionnaire!O$5:O$55="Partial")*Methodology!$B$28+(Questionnaire!O$5:O$55="No")*Methodology!$B$29))/SUMPRODUCT((Questionnaire!$B$5:$B$55=I$5)*Questionnaire!$E$5:$E$55*((Questionnaire!O$5:O$55="Yes")+(Questionnaire!O$5:O$55="Partial")+(Questionnaire!O$5:O$55="No"))),"N/A")) -> 0.66666667 | J11: =IF($A11="","",IFERROR(SUMPRODUCT((Questionnaire!$B$5:$B$55=J$5)*Questionnaire!$E$5:$E$55*((Questionnaire!O$5:O$55="Yes")*Methodology!$B$27+(Questionnaire!O$5:O$55="Partial")*Methodology!$B$28+(Questionnaire!O$5:O$55="No")*Methodology!$B$29))/SUMPRODUCT((Questionnaire!$B$5:$B$55=J$5)*Questionnaire!$E$5:$E$55*((Questionnaire!O$5:O$55="Yes")+(Questionnaire!O$5:O$55="Partial")+(Questionnaire!O$5:O$55="No"))),"N/A")) -> 0.45833333 | K11: =IF($A11="","",IFERROR(SUMPRODUCT((Questionnaire!$B$5:$B$55=K$5)*Questionnaire!$E$5:$E$55*((Questionnaire!O$5:O$55="Yes")*Methodology!$B$27+(Questionnaire!O$5:O$55="Partial")*Methodology!$B$28+(Questionnaire!O$5:O$55="No")*Methodology!$B$29))/SUMPRODUCT((Questionnaire!$B$5:$B$55=K$5)*Questionnaire!$E$5:$E$55*((Questionnaire!O$5:O$55="Yes")+(Questionnaire!O$5:O$55="Partial")+(Questionnaire!O$5:O$55="No"))),"N/A")) -> 0.5 | L11: =IF($A11="","",IFERROR(SUMPRODUCT((Questionnaire!$B$5:$B$55=L$5)*Questionnaire!$E$5:$E$55*((Questionnaire!O$5:O$55="Yes")*Methodology!$B$27+(Questionnaire!O$5:O$55="Partial")*Methodology!$B$28+(Questionnaire!O$5:O$55="No")*Methodology!$B$29))/SUMPRODUCT((Questionnaire!$B$5:$B$55=L$5)*Questionnaire!$E$5:$E$55*((Questionnaire!O$5:O$55="Yes")+(Questionnaire!O$5:O$55="Partial")+(Questionnaire!O$5:O$55="No"))),"N/A")) -> 0.625 | M11: =IF($A11="","",IFERROR(SUMPRODUCT((Questionnaire!$B$5:$B$55=M$5)*Questionnaire!$E$5:$E$55*((Questionnaire!O$5:O$55="Yes")*Methodology!$B$27+(Questionnaire!O$5:O$55="Partial")*Methodology!$B$28+(Questionnaire!O$5:O$55="No")*Methodology!$B$29))/SUMPRODUCT((Questionnaire!$B$5:$B$55=M$5)*Questionnaire!$E$5:$E$55*((Questionnaire!O$5:O$55="Yes")+(Questionnaire!O$5:O$55="Partial")+(Questionnaire!O$5:O$55="No"))),"N/A")) -> 0.64285714 | N11: =IF($A11="","",IFERROR(SUMPRODUCT((Questionnaire!$B$5:$B$55=N$5)*Questionnaire!$E$5:$E$55*((Questionnaire!O$5:O$55="Yes")*Methodology!$B$27+(Questionnaire!O$5:O$55="Partial")*Methodology!$B$28+(Questionnaire!O$5:O$55="No")*Methodology!$B$29))/SUMPRODUCT((Questionnaire!$B$5:$B$55=N$5)*Questionnaire!$E$5:$E$55*((Questionnaire!O$5:O$55="Yes")+(Questionnaire!O$5:O$55="Partial")+(Questionnaire!O$5:O$55="No"))),"N/A")) -> 0.75 | O11: =IF($A11="","",IFERROR(SUMPRODUCT((Questionnaire!$B$5:$B$55=O$5)*Questionnaire!$E$5:$E$55*((Questionnaire!O$5:O$55="Yes")*Methodology!$B$27+(Questionnaire!O$5:O$55="Partial")*Methodology!$B$28+(Questionnaire!O$5:O$55="No")*Methodology!$B$29))/SUMPRODUCT((Questionnaire!$B$5:$B$55=O$5)*Questionnaire!$E$5:$E$55*((Questionnaire!O$5:O$55="Yes")+(Questionnaire!O$5:O$55="Partial")+(Questionnaire!O$5:O$55="No"))),"N/A")) -> N/A
A12: =IF(Vendor_Register!A12="","",Vendor_Register!A12) | B12: =IF(A12="","",Vendor_Register!B12) | C12: =IF($A12="","",IFERROR(SUMPRODUCT(Questionnaire!$E$5:$E$55*((Questionnaire!P$5:P$55="Yes")*Methodology!$B$27+(Questionnaire!P$5:P$55="Partial")*Methodology!$B$28+(Questionnaire!P$5:P$55="No")*Methodology!$B$29))/SUMPRODUCT(Questionnaire!$E$5:$E$55*((Questionnaire!P$5:P$55="Yes")+(Questionnaire!P$5:P$55="Partial")+(Questionnaire!P$5:P$55="No"))),"")) | D12: =IF($A12="","",SUMPRODUCT(--(Questionnaire!P$5:P$55<>""))/ROWS(Questionnaire!$A$5:$A$55)) | E12: =IF($A12="","",SUMPRODUCT((Questionnaire!$F$5:$F$55="Yes")*(Questionnaire!P$5:P$55="No"))) | F12: =IF($A12="","",IFERROR(SUMPRODUCT((Questionnaire!$B$5:$B$55=F$5)*Questionnaire!$E$5:$E$55*((Questionnaire!P$5:P$55="Yes")*Methodology!$B$27+(Questionnaire!P$5:P$55="Partial")*Methodology!$B$28+(Questionnaire!P$5:P$55="No")*Methodology!$B$29))/SUMPRODUCT((Questionnaire!$B$5:$B$55=F$5)*Questionnaire!$E$5:$E$55*((Questionnaire!P$5:P$55="Yes")+(Questionnaire!P$5:P$55="Partial")+(Questionnaire!P$5:P$55="No"))),"N/A")) | G12: =IF($A12="","",IFERROR(SUMPRODUCT((Questionnaire!$B$5:$B$55=G$5)*Questionnaire!$E$5:$E$55*((Questionnaire!P$5:P$55="Yes")*Methodology!$B$27+(Questionnaire!P$5:P$55="Partial")*Methodology!$B$28+(Questionnaire!P$5:P$55="No")*Methodology!$B$29))/SUMPRODUCT((Questionnaire!$B$5:$B$55=G$5)*Questionnaire!$E$5:$E$55*((Questionnaire!P$5:P$55="Yes")+(Questionnaire!P$5:P$55="Partial")+(Questionnaire!P$5:P$55="No"))),"N/A")) | H12: =IF($A12="","",IFERROR(SUMPRODUCT((Questionnaire!$B$5:$B$55=H$5)*Questionnaire!$E$5:$E$55*((Questionnaire!P$5:P$55="Yes")*Methodology!$B$27+(Questionnaire!P$5:P$55="Partial")*Methodology!$B$28+(Questionnaire!P$5:P$55="No")*Methodology!$B$29))/SUMPRODUCT((Questionnaire!$B$5:$B$55=H$5)*Questionnaire!$E$5:$E$55*((Questionnaire!P$5:P$55="Yes")+(Questionnaire!P$5:P$55="Partial")+(Questionnaire!P$5:P$55="No"))),"N/A")) | I12: =IF($A12="","",IFERROR(SUMPRODUCT((Questionnaire!$B$5:$B$55=I$5)*Questionnaire!$E$5:$E$55*((Questionnaire!P$5:P$55="Yes")*Methodology!$B$27+(Questionnaire!P$5:P$55="Partial")*Methodology!$B$28+(Questionnaire!P$5:P$55="No")*Methodology!$B$29))/SUMPRODUCT((Questionnaire!$B$5:$B$55=I$5)*Questionnaire!$E$5:$E$55*((Questionnaire!P$5:P$55="Yes")+(Questionnaire!P$5:P$55="Partial")+(Questionnaire!P$5:P$55="No"))),"N/A")) | J12: =IF($A12="","",IFERROR(SUMPRODUCT((Questionnaire!$B$5:$B$55=J$5)*Questionnaire!$E$5:$E$55*((Questionnaire!P$5:P$55="Yes")*Methodology!$B$27+(Questionnaire!P$5:P$55="Partial")*Methodology!$B$28+(Questionnaire!P$5:P$55="No")*Methodology!$B$29))/SUMPRODUCT((Questionnaire!$B$5:$B$55=J$5)*Questionnaire!$E$5:$E$55*((Questionnaire!P$5:P$55="Yes")+(Questionnaire!P$5:P$55="Partial")+(Questionnaire!P$5:P$55="No"))),"N/A")) | K12: =IF($A12="","",IFERROR(SUMPRODUCT((Questionnaire!$B$5:$B$55=K$5)*Questionnaire!$E$5:$E$55*((Questionnaire!P$5:P$55="Yes")*Methodology!$B$27+(Questionnaire!P$5:P$55="Partial")*Methodology!$B$28+(Questionnaire!P$5:P$55="No")*Methodology!$B$29))/SUMPRODUCT((Questionnaire!$B$5:$B$55=K$5)*Questionnaire!$E$5:$E$55*((Questionnaire!P$5:P$55="Yes")+(Questionnaire!P$5:P$55="Partial")+(Questionnaire!P$5:P$55="No"))),"N/A")) | L12: =IF($A12="","",IFERROR(SUMPRODUCT((Questionnaire!$B$5:$B$55=L$5)*Questionnaire!$E$5:$E$55*((Questionnaire!P$5:P$55="Yes")*Methodology!$B$27+(Questionnaire!P$5:P$55="Partial")*Methodology!$B$28+(Questionnaire!P$5:P$55="No")*Methodology!$B$29))/SUMPRODUCT((Questionnaire!$B$5:$B$55=L$5)*Questionnaire!$E$5:$E$55*((Questionnaire!P$5:P$55="Yes")+(Questionnaire!P$5:P$55="Partial")+(Questionnaire!P$5:P$55="No"))),"N/A")) | M12: =IF($A12="","",IFERROR(SUMPRODUCT((Questionnaire!$B$5:$B$55=M$5)*Questionnaire!$E$5:$E$55*((Questionnaire!P$5:P$55="Yes")*Methodology!$B$27+(Questionnaire!P$5:P$55="Partial")*Methodology!$B$28+(Questionnaire!P$5:P$55="No")*Methodology!$B$29))/SUMPRODUCT((Questionnaire!$B$5:$B$55=M$5)*Questionnaire!$E$5:$E$55*((Questionnaire!P$5:P$55="Yes")+(Questionnaire!P$5:P$55="Partial")+(Questionnaire!P$5:P$55="No"))),"N/A")) | N12: =IF($A12="","",IFERROR(SUMPRODUCT((Questionnaire!$B$5:$B$55=N$5)*Questionnaire!$E$5:$E$55*((Questionnaire!P$5:P$55="Yes")*Methodology!$B$27+(Questionnaire!P$5:P$55="Partial")*Methodology!$B$28+(Questionnaire!P$5:P$55="No")*Methodology!$B$29))/SUMPRODUCT((Questionnaire!$B$5:$B$55=N$5)*Questionnaire!$E$5:$E$55*((Questionnaire!P$5:P$55="Yes")+(Questionnaire!P$5:P$55="Partial")+(Questionnaire!P$5:P$55="No"))),"N/A")) | O12: =IF($A12="","",IFERROR(SUMPRODUCT((Questionnaire!$B$5:$B$55=O$5)*Questionnaire!$E$5:$E$55*((Questionnaire!P$5:P$55="Yes")*Methodology!$B$27+(Questionnaire!P$5:P$55="Partial")*Methodology!$B$28+(Questionnaire!P$5:P$55="No")*Methodology!$B$29))/SUMPRODUCT((Questionnaire!$B$5:$B$55=O$5)*Questionnaire!$E$5:$E$55*((Questionnaire!P$5:P$55="Yes")+(Questionnaire!P$5:P$55="Partial")+(Questionnaire!P$5:P$55="No"))),"N/A"))
A13: =IF(Vendor_Register!A13="","",Vendor_Register!A13) | B13: =IF(A13="","",Vendor_Register!B13) | C13: =IF($A13="","",IFERROR(SUMPRODUCT(Questionnaire!$E$5:$E$55*((Questionnaire!Q$5:Q$55="Yes")*Methodology!$B$27+(Questionnaire!Q$5:Q$55="Partial")*Methodology!$B$28+(Questionnaire!Q$5:Q$55="No")*Methodology!$B$29))/SUMPRODUCT(Questionnaire!$E$5:$E$55*((Questionnaire!Q$5:Q$55="Yes")+(Questionnaire!Q$5:Q$55="Partial")+(Questionnaire!Q$5:Q$55="No"))),"")) | D13: =IF($A13="","",SUMPRODUCT(--(Questionnaire!Q$5:Q$55<>""))/ROWS(Questionnaire!$A$5:$A$55)) | E13: =IF($A13="","",SUMPRODUCT((Questionnaire!$F$5:$F$55="Yes")*(Questionnaire!Q$5:Q$55="No"))) | F13: =IF($A13="","",IFERROR(SUMPRODUCT((Questionnaire!$B$5:$B$55=F$5)*Questionnaire!$E$5:$E$55*((Questionnaire!Q$5:Q$55="Yes")*Methodology!$B$27+(Questionnaire!Q$5:Q$55="Partial")*Methodology!$B$28+(Questionnaire!Q$5:Q$55="No")*Methodology!$B$29))/SUMPRODUCT((Questionnaire!$B$5:$B$55=F$5)*Questionnaire!$E$5:$E$55*((Questionnaire!Q$5:Q$55="Yes")+(Questionnaire!Q$5:Q$55="Partial")+(Questionnaire!Q$5:Q$55="No"))),"N/A")) | G13: =IF($A13="","",IFERROR(SUMPRODUCT((Questionnaire!$B$5:$B$55=G$5)*Questionnaire!$E$5:$E$55*((Questionnaire!Q$5:Q$55="Yes")*Methodology!$B$27+(Questionnaire!Q$5:Q$55="Partial")*Methodology!$B$28+(Questionnaire!Q$5:Q$55="No")*Methodology!$B$29))/SUMPRODUCT((Questionnaire!$B$5:$B$55=G$5)*Questionnaire!$E$5:$E$55*((Questionnaire!Q$5:Q$55="Yes")+(Questionnaire!Q$5:Q$55="Partial")+(Questionnaire!Q$5:Q$55="No"))),"N/A")) | H13: =IF($A13="","",IFERROR(SUMPRODUCT((Questionnaire!$B$5:$B$55=H$5)*Questionnaire!$E$5:$E$55*((Questionnaire!Q$5:Q$55="Yes")*Methodology!$B$27+(Questionnaire!Q$5:Q$55="Partial")*Methodology!$B$28+(Questionnaire!Q$5:Q$55="No")*Methodology!$B$29))/SUMPRODUCT((Questionnaire!$B$5:$B$55=H$5)*Questionnaire!$E$5:$E$55*((Questionnaire!Q$5:Q$55="Yes")+(Questionnaire!Q$5:Q$55="Partial")+(Questionnaire!Q$5:Q$55="No"))),"N/A")) | I13: =IF($A13="","",IFERROR(SUMPRODUCT((Questionnaire!$B$5:$B$55=I$5)*Questionnaire!$E$5:$E$55*((Questionnaire!Q$5:Q$55="Yes")*Methodology!$B$27+(Questionnaire!Q$5:Q$55="Partial")*Methodology!$B$28+(Questionnaire!Q$5:Q$55="No")*Methodology!$B$29))/SUMPRODUCT((Questionnaire!$B$5:$B$55=I$5)*Questionnaire!$E$5:$E$55*((Questionnaire!Q$5:Q$55="Yes")+(Questionnaire!Q$5:Q$55="Partial")+(Questionnaire!Q$5:Q$55="No"))),"N/A")) | J13: =IF($A13="","",IFERROR(SUMPRODUCT((Questionnaire!$B$5:$B$55=J$5)*Questionnaire!$E$5:$E$55*((Questionnaire!Q$5:Q$55="Yes")*Methodology!$B$27+(Questionnaire!Q$5:Q$55="Partial")*Methodology!$B$28+(Questionnaire!Q$5:Q$55="No")*Methodology!$B$29))/SUMPRODUCT((Questionnaire!$B$5:$B$55=J$5)*Questionnaire!$E$5:$E$55*((Questionnaire!Q$5:Q$55="Yes")+(Questionnaire!Q$5:Q$55="Partial")+(Questionnaire!Q$5:Q$55="No"))),"N/A")) | K13: =IF($A13="","",IFERROR(SUMPRODUCT((Questionnaire!$B$5:$B$55=K$5)*Questionnaire!$E$5:$E$55*((Questionnaire!Q$5:Q$55="Yes")*Methodology!$B$27+(Questionnaire!Q$5:Q$55="Partial")*Methodology!$B$28+(Questionnaire!Q$5:Q$55="No")*Methodology!$B$29))/SUMPRODUCT((Questionnaire!$B$5:$B$55=K$5)*Questionnaire!$E$5:$E$55*((Questionnaire!Q$5:Q$55="Yes")+(Questionnaire!Q$5:Q$55="Partial")+(Questionnaire!Q$5:Q$55="No"))),"N/A")) | L13: =IF($A13="","",IFERROR(SUMPRODUCT((Questionnaire!$B$5:$B$55=L$5)*Questionnaire!$E$5:$E$55*((Questionnaire!Q$5:Q$55="Yes")*Methodology!$B$27+(Questionnaire!Q$5:Q$55="Partial")*Methodology!$B$28+(Questionnaire!Q$5:Q$55="No")*Methodology!$B$29))/SUMPRODUCT((Questionnaire!$B$5:$B$55=L$5)*Questionnaire!$E$5:$E$55*((Questionnaire!Q$5:Q$55="Yes")+(Questionnaire!Q$5:Q$55="Partial")+(Questionnaire!Q$5:Q$55="No"))),"N/A")) | M13: =IF($A13="","",IFERROR(SUMPRODUCT((Questionnaire!$B$5:$B$55=M$5)*Questionnaire!$E$5:$E$55*((Questionnaire!Q$5:Q$55="Yes")*Methodology!$B$27+(Questionnaire!Q$5:Q$55="Partial")*Methodology!$B$28+(Questionnaire!Q$5:Q$55="No")*Methodology!$B$29))/SUMPRODUCT((Questionnaire!$B$5:$B$55=M$5)*Questionnaire!$E$5:$E$55*((Questionnaire!Q$5:Q$55="Yes")+(Questionnaire!Q$5:Q$55="Partial")+(Questionnaire!Q$5:Q$55="No"))),"N/A")) | N13: =IF($A13="","",IFERROR(SUMPRODUCT((Questionnaire!$B$5:$B$55=N$5)*Questionnaire!$E$5:$E$55*((Questionnaire!Q$5:Q$55="Yes")*Methodology!$B$27+(Questionnaire!Q$5:Q$55="Partial")*Methodology!$B$28+(Questionnaire!Q$5:Q$55="No")*Methodology!$B$29))/SUMPRODUCT((Questionnaire!$B$5:$B$55=N$5)*Questionnaire!$E$5:$E$55*((Questionnaire!Q$5:Q$55="Yes")+(Questionnaire!Q$5:Q$55="Partial")+(Questionnaire!Q$5:Q$55="No"))),"N/A")) | O13: =IF($A13="","",IFERROR(SUMPRODUCT((Questionnaire!$B$5:$B$55=O$5)*Questionnaire!$E$5:$E$55*((Questionnaire!Q$5:Q$55="Yes")*Methodology!$B$27+(Questionnaire!Q$5:Q$55="Partial")*Methodology!$B$28+(Questionnaire!Q$5:Q$55="No")*Methodology!$B$29))/SUMPRODUCT((Questionnaire!$B$5:$B$55=O$5)*Questionnaire!$E$5:$E$55*((Questionnaire!Q$5:Q$55="Yes")+(Questionnaire!Q$5:Q$55="Partial")+(Questionnaire!Q$5:Q$55="No"))),"N/A"))
A14: =IF(Vendor_Register!A14="","",Vendor_Register!A14) | B14: =IF(A14="","",Vendor_Register!B14) | C14: =IF($A14="","",IFERROR(SUMPRODUCT(Questionnaire!$E$5:$E$55*((Questionnaire!R$5:R$55="Yes")*Methodology!$B$27+(Questionnaire!R$5:R$55="Partial")*Methodology!$B$28+(Questionnaire!R$5:R$55="No")*Methodology!$B$29))/SUMPRODUCT(Questionnaire!$E$5:$E$55*((Questionnaire!R$5:R$55="Yes")+(Questionnaire!R$5:R$55="Partial")+(Questionnaire!R$5:R$55="No"))),"")) | D14: =IF($A14="","",SUMPRODUCT(--(Questionnaire!R$5:R$55<>""))/ROWS(Questionnaire!$A$5:$A$55)) | E14: =IF($A14="","",SUMPRODUCT((Questionnaire!$F$5:$F$55="Yes")*(Questionnaire!R$5:R$55="No"))) | F14: =IF($A14="","",IFERROR(SUMPRODUCT((Questionnaire!$B$5:$B$55=F$5)*Questionnaire!$E$5:$E$55*((Questionnaire!R$5:R$55="Yes")*Methodology!$B$27+(Questionnaire!R$5:R$55="Partial")*Methodology!$B$28+(Questionnaire!R$5:R$55="No")*Methodology!$B$29))/SUMPRODUCT((Questionnaire!$B$5:$B$55=F$5)*Questionnaire!$E$5:$E$55*((Questionnaire!R$5:R$55="Yes")+(Questionnaire!R$5:R$55="Partial")+(Questionnaire!R$5:R$55="No"))),"N/A")) | G14: =IF($A14="","",IFERROR(SUMPRODUCT((Questionnaire!$B$5:$B$55=G$5)*Questionnaire!$E$5:$E$55*((Questionnaire!R$5:R$55="Yes")*Methodology!$B$27+(Questionnaire!R$5:R$55="Partial")*Methodology!$B$28+(Questionnaire!R$5:R$55="No")*Methodology!$B$29))/SUMPRODUCT((Questionnaire!$B$5:$B$55=G$5)*Questionnaire!$E$5:$E$55*((Questionnaire!R$5:R$55="Yes")+(Questionnaire!R$5:R$55="Partial")+(Questionnaire!R$5:R$55="No"))),"N/A")) | H14: =IF($A14="","",IFERROR(SUMPRODUCT((Questionnaire!$B$5:$B$55=H$5)*Questionnaire!$E$5:$E$55*((Questionnaire!R$5:R$55="Yes")*Methodology!$B$27+(Questionnaire!R$5:R$55="Partial")*Methodology!$B$28+(Questionnaire!R$5:R$55="No")*Methodology!$B$29))/SUMPRODUCT((Questionnaire!$B$5:$B$55=H$5)*Questionnaire!$E$5:$E$55*((Questionnaire!R$5:R$55="Yes")+(Questionnaire!R$5:R$55="Partial")+(Questionnaire!R$5:R$55="No"))),"N/A")) | I14: =IF($A14="","",IFERROR(SUMPRODUCT((Questionnaire!$B$5:$B$55=I$5)*Questionnaire!$E$5:$E$55*((Questionnaire!R$5:R$55="Yes")*Methodology!$B$27+(Questionnaire!R$5:R$55="Partial")*Methodology!$B$28+(Questionnaire!R$5:R$55="No")*Methodology!$B$29))/SUMPRODUCT((Questionnaire!$B$5:$B$55=I$5)*Questionnaire!$E$5:$E$55*((Questionnaire!R$5:R$55="Yes")+(Questionnaire!R$5:R$55="Partial")+(Questionnaire!R$5:R$55="No"))),"N/A")) | J14: =IF($A14="","",IFERROR(SUMPRODUCT((Questionnaire!$B$5:$B$55=J$5)*Questionnaire!$E$5:$E$55*((Questionnaire!R$5:R$55="Yes")*Methodology!$B$27+(Questionnaire!R$5:R$55="Partial")*Methodology!$B$28+(Questionnaire!R$5:R$55="No")*Methodology!$B$29))/SUMPRODUCT((Questionnaire!$B$5:$B$55=J$5)*Questionnaire!$E$5:$E$55*((Questionnaire!R$5:R$55="Yes")+(Questionnaire!R$5:R$55="Partial")+(Questionnaire!R$5:R$55="No"))),"N/A")) | K14: =IF($A14="","",IFERROR(SUMPRODUCT((Questionnaire!$B$5:$B$55=K$5)*Questionnaire!$E$5:$E$55*((Questionnaire!R$5:R$55="Yes")*Methodology!$B$27+(Questionnaire!R$5:R$55="Partial")*Methodology!$B$28+(Questionnaire!R$5:R$55="No")*Methodology!$B$29))/SUMPRODUCT((Questionnaire!$B$5:$B$55=K$5)*Questionnaire!$E$5:$E$55*((Questionnaire!R$5:R$55="Yes")+(Questionnaire!R$5:R$55="Partial")+(Questionnaire!R$5:R$55="No"))),"N/A")) | L14: =IF($A14="","",IFERROR(SUMPRODUCT((Questionnaire!$B$5:$B$55=L$5)*Questionnaire!$E$5:$E$55*((Questionnaire!R$5:R$55="Yes")*Methodology!$B$27+(Questionnaire!R$5:R$55="Partial")*Methodology!$B$28+(Questionnaire!R$5:R$55="No")*Methodology!$B$29))/SUMPRODUCT((Questionnaire!$B$5:$B$55=L$5)*Questionnaire!$E$5:$E$55*((Questionnaire!R$5:R$55="Yes")+(Questionnaire!R$5:R$55="Partial")+(Questionnaire!R$5:R$55="No"))),"N/A")) | M14: =IF($A14="","",IFERROR(SUMPRODUCT((Questionnaire!$B$5:$B$55=M$5)*Questionnaire!$E$5:$E$55*((Questionnaire!R$5:R$55="Yes")*Methodology!$B$27+(Questionnaire!R$5:R$55="Partial")*Methodology!$B$28+(Questionnaire!R$5:R$55="No")*Methodology!$B$29))/SUMPRODUCT((Questionnaire!$B$5:$B$55=M$5)*Questionnaire!$E$5:$E$55*((Questionnaire!R$5:R$55="Yes")+(Questionnaire!R$5:R$55="Partial")+(Questionnaire!R$5:R$55="No"))),"N/A")) | N14: =IF($A14="","",IFERROR(SUMPRODUCT((Questionnaire!$B$5:$B$55=N$5)*Questionnaire!$E$5:$E$55*((Questionnaire!R$5:R$55="Yes")*Methodology!$B$27+(Questionnaire!R$5:R$55="Partial")*Methodology!$B$28+(Questionnaire!R$5:R$55="No")*Methodology!$B$29))/SUMPRODUCT((Questionnaire!$B$5:$B$55=N$5)*Questionnaire!$E$5:$E$55*((Questionnaire!R$5:R$55="Yes")+(Questionnaire!R$5:R$55="Partial")+(Questionnaire!R$5:R$55="No"))),"N/A")) | O14: =IF($A14="","",IFERROR(SUMPRODUCT((Questionnaire!$B$5:$B$55=O$5)*Questionnaire!$E$5:$E$55*((Questionnaire!R$5:R$55="Yes")*Methodology!$B$27+(Questionnaire!R$5:R$55="Partial")*Methodology!$B$28+(Questionnaire!R$5:R$55="No")*Methodology!$B$29))/SUMPRODUCT((Questionnaire!$B$5:$B$55=O$5)*Questionnaire!$E$5:$E$55*((Questionnaire!R$5:R$55="Yes")+(Questionnaire!R$5:R$55="Partial")+(Questionnaire!R$5:R$55="No"))),"N/A"))
A15: =IF(Vendor_Register!A15="","",Vendor_Register!A15) | B15: =IF(A15="","",Vendor_Register!B15) | C15: =IF($A15="","",IFERROR(SUMPRODUCT(Questionnaire!$E$5:$E$55*((Questionnaire!S$5:S$55="Yes")*Methodology!$B$27+(Questionnaire!S$5:S$55="Partial")*Methodology!$B$28+(Questionnaire!S$5:S$55="No")*Methodology!$B$29))/SUMPRODUCT(Questionnaire!$E$5:$E$55*((Questionnaire!S$5:S$55="Yes")+(Questionnaire!S$5:S$55="Partial")+(Questionnaire!S$5:S$55="No"))),"")) | D15: =IF($A15="","",SUMPRODUCT(--(Questionnaire!S$5:S$55<>""))/ROWS(Questionnaire!$A$5:$A$55)) | E15: =IF($A15="","",SUMPRODUCT((Questionnaire!$F$5:$F$55="Yes")*(Questionnaire!S$5:S$55="No"))) | F15: =IF($A15="","",IFERROR(SUMPRODUCT((Questionnaire!$B$5:$B$55=F$5)*Questionnaire!$E$5:$E$55*((Questionnaire!S$5:S$55="Yes")*Methodology!$B$27+(Questionnaire!S$5:S$55="Partial")*Methodology!$B$28+(Questionnaire!S$5:S$55="No")*Methodology!$B$29))/SUMPRODUCT((Questionnaire!$B$5:$B$55=F$5)*Questionnaire!$E$5:$E$55*((Questionnaire!S$5:S$55="Yes")+(Questionnaire!S$5:S$55="Partial")+(Questionnaire!S$5:S$55="No"))),"N/A")) | G15: =IF($A15="","",IFERROR(SUMPRODUCT((Questionnaire!$B$5:$B$55=G$5)*Questionnaire!$E$5:$E$55*((Questionnaire!S$5:S$55="Yes")*Methodology!$B$27+(Questionnaire!S$5:S$55="Partial")*Methodology!$B$28+(Questionnaire!S$5:S$55="No")*Methodology!$B$29))/SUMPRODUCT((Questionnaire!$B$5:$B$55=G$5)*Questionnaire!$E$5:$E$55*((Questionnaire!S$5:S$55="Yes")+(Questionnaire!S$5:S$55="Partial")+(Questionnaire!S$5:S$55="No"))),"N/A")) | H15: =IF($A15="","",IFERROR(SUMPRODUCT((Questionnaire!$B$5:$B$55=H$5)*Questionnaire!$E$5:$E$55*((Questionnaire!S$5:S$55="Yes")*Methodology!$B$27+(Questionnaire!S$5:S$55="Partial")*Methodology!$B$28+(Questionnaire!S$5:S$55="No")*Methodology!$B$29))/SUMPRODUCT((Questionnaire!$B$5:$B$55=H$5)*Questionnaire!$E$5:$E$55*((Questionnaire!S$5:S$55="Yes")+(Questionnaire!S$5:S$55="Partial")+(Questionnaire!S$5:S$55="No"))),"N/A")) | I15: =IF($A15="","",IFERROR(SUMPRODUCT((Questionnaire!$B$5:$B$55=I$5)*Questionnaire!$E$5:$E$55*((Questionnaire!S$5:S$55="Yes")*Methodology!$B$27+(Questionnaire!S$5:S$55="Partial")*Methodology!$B$28+(Questionnaire!S$5:S$55="No")*Methodology!$B$29))/SUMPRODUCT((Questionnaire!$B$5:$B$55=I$5)*Questionnaire!$E$5:$E$55*((Questionnaire!S$5:S$55="Yes")+(Questionnaire!S$5:S$55="Partial")+(Questionnaire!S$5:S$55="No"))),"N/A")) | J15: =IF($A15="","",IFERROR(SUMPRODUCT((Questionnaire!$B$5:$B$55=J$5)*Questionnaire!$E$5:$E$55*((Questionnaire!S$5:S$55="Yes")*Methodology!$B$27+(Questionnaire!S$5:S$55="Partial")*Methodology!$B$28+(Questionnaire!S$5:S$55="No")*Methodology!$B$29))/SUMPRODUCT((Questionnaire!$B$5:$B$55=J$5)*Questionnaire!$E$5:$E$55*((Questionnaire!S$5:S$55="Yes")+(Questionnaire!S$5:S$55="Partial")+(Questionnaire!S$5:S$55="No"))),"N/A")) | K15: =IF($A15="","",IFERROR(SUMPRODUCT((Questionnaire!$B$5:$B$55=K$5)*Questionnaire!$E$5:$E$55*((Questionnaire!S$5:S$55="Yes")*Methodology!$B$27+(Questionnaire!S$5:S$55="Partial")*Methodology!$B$28+(Questionnaire!S$5:S$55="No")*Methodology!$B$29))/SUMPRODUCT((Questionnaire!$B$5:$B$55=K$5)*Questionnaire!$E$5:$E$55*((Questionnaire!S$5:S$55="Yes")+(Questionnaire!S$5:S$55="Partial")+(Questionnaire!S$5:S$55="No"))),"N/A")) | L15: =IF($A15="","",IFERROR(SUMPRODUCT((Questionnaire!$B$5:$B$55=L$5)*Questionnaire!$E$5:$E$55*((Questionnaire!S$5:S$55="Yes")*Methodology!$B$27+(Questionnaire!S$5:S$55="Partial")*Methodology!$B$28+(Questionnaire!S$5:S$55="No")*Methodology!$B$29))/SUMPRODUCT((Questionnaire!$B$5:$B$55=L$5)*Questionnaire!$E$5:$E$55*((Questionnaire!S$5:S$55="Yes")+(Questionnaire!S$5:S$55="Partial")+(Questionnaire!S$5:S$55="No"))),"N/A")) | M15: =IF($A15="","",IFERROR(SUMPRODUCT((Questionnaire!$B$5:$B$55=M$5)*Questionnaire!$E$5:$E$55*((Questionnaire!S$5:S$55="Yes")*Methodology!$B$27+(Questionnaire!S$5:S$55="Partial")*Methodology!$B$28+(Questionnaire!S$5:S$55="No")*Methodology!$B$29))/SUMPRODUCT((Questionnaire!$B$5:$B$55=M$5)*Questionnaire!$E$5:$E$55*((Questionnaire!S$5:S$55="Yes")+(Questionnaire!S$5:S$55="Partial")+(Questionnaire!S$5:S$55="No"))),"N/A")) | N15: =IF($A15="","",IFERROR(SUMPRODUCT((Questionnaire!$B$5:$B$55=N$5)*Questionnaire!$E$5:$E$55*((Questionnaire!S$5:S$55="Yes")*Methodology!$B$27+(Questionnaire!S$5:S$55="Partial")*Methodology!$B$28+(Questionnaire!S$5:S$55="No")*Methodology!$B$29))/SUMPRODUCT((Questionnaire!$B$5:$B$55=N$5)*Questionnaire!$E$5:$E$55*((Questionnaire!S$5:S$55="Yes")+(Questionnaire!S$5:S$55="Partial")+(Questionnaire!S$5:S$55="No"))),"N/A")) | O15: =IF($A15="","",IFERROR(SUMPRODUCT((Questionnaire!$B$5:$B$55=O$5)*Questionnaire!$E$5:$E$55*((Questionnaire!S$5:S$55="Yes")*Methodology!$B$27+(Questionnaire!S$5:S$55="Partial")*Methodology!$B$28+(Questionnaire!S$5:S$55="No")*Methodology!$B$29))/SUMPRODUCT((Questionnaire!$B$5:$B$55=O$5)*Questionnaire!$E$5:$E$55*((Questionnaire!S$5:S$55="Yes")+(Questionnaire!S$5:S$55="Partial")+(Questionnaire!S$5:S$55="No"))),"N/A"))
A17: Shading: green ≥ 90% | orange < 60% | 'N/A' = no applicable questions answered for that domain. Control effectiveness feeds the residual risk score in Vendor_Register.

Sheet Due_Diligence
A1: Vendor Due Diligence Checklist
A2: Select a vendor in B3, then work through the checklist. Mark items that do not apply to this vendor type as N/A.
A3: Vendor ID: | B3: V-002 | C3: =IFERROR(INDEX(Vendor_Register!$B$6:$B$15,MATCH($B$3,Vendor_Register!$A$6:$A$15,0)),"") -> NimbusAI Language Platform
A4: Category: | B4: =IFERROR(INDEX(Vendor_Register!$D$6:$D$15,MATCH($B$3,Vendor_Register!$A$6:$A$15,0)),"") -> AI/ML Software
A5: Inherent rating: | B5: =IFERROR(INDEX(Vendor_Register!$M$6:$M$15,MATCH($B$3,Vendor_Register!$A$6:$A$15,0)),"") -> High
A6: Checklist completion: | B6: =IFERROR(COUNTIF(G9:G42,"Complete")/(COUNTA(A9:A42)-COUNTIF(G9:G42,"N/A")),0) -> 0.35483871 | C6: =COUNTIF(G9:G42,"Exception")&" open exception(s)" -> 1 open exception(s)
A8: Ref | B8: Phase | C8: Requirement | D8: Applies to | E8: Evidence / deliverable | F8: Responsible | G8: Status | H8: Reviewer | I8: Date completed | J8: Findings / notes
A9: DD-01 | B9: 1. Identification & business case | C9: Business justification, data-flow description and business owner documented | D9: All | E9: Vendor intake form | F9: Business Owner | G9: Complete | H9: A. Khan | I9: 46296
A10: DD-02 | B10: 1. Identification & business case | C10: Inherent risk triage completed (six factor scores and rating recorded in Vendor_Register) | D10: All | E10: Vendor_Register entry | F10: GRC Analyst | G10: Complete | H10: A. Khan | I10: 46297
A11: DD-03 | B11: 1. Identification & business case | C11: Legal entity, ownership and registration verified; sanctions and adverse-media screening completed | D11: All | E11: Screening report | F11: Procurement / Legal | G11: Complete | H11: R. Malik | I11: 46300
A12: DD-04 | B12: 1. Identification & business case | C12: Financial stability reviewed (financial statements, credit report or funding status) | D12: All | E12: Financial review note | F12: Procurement / Finance | G12: Complete | H12: R. Malik | I12: 46300
A13: DD-05 | B13: 2. Security assurance | C13: Security questionnaire completed by vendor, scored and answers challenged where evidence is missing | D13: All | E13: Questionnaire; Assessment_Results | F13: GRC Analyst | G13: Complete | H13: A. Khan | I13: 46309
A14: DD-06 | B14: 2. Security assurance | C14: SOC 2 Type II or ISO/IEC 27001 certificate reviewed: scope, period, auditor opinion, exceptions and complementary user-entity controls | D14: All | E14: Report review memo | F14: Security Analyst | G14: Complete | H14: S. Ahmed | I14: 46310 | J14: SOC 2 Type I only; Type II audit period ends Dec 2026.
A15: DD-07 | B15: 2. Security assurance | C15: Penetration test summary (within 12 months) reviewed; remediation status confirmed | D15: All | E15: Pen test executive summary | F15: Security Analyst | G15: In Progress
A16: DD-08 | B16: 2. Security assurance | C16: Architecture and data flows reviewed: encryption, key management, tenancy model, integrations | D16: All | E16: Architecture review notes | F16: Security Architect | G16: Complete | H16: S. Ahmed | I16: 46311
A17: DD-09 | B17: 2. Security assurance | C17: Vulnerability management SLAs and secure development evidence reviewed | D17: All | E17: Policies; metrics | F17: Security Analyst | G17: In Progress
A18: DD-10 | B18: 2. Security assurance | C18: Core policies sampled (access control, incident response, business continuity) | D18: All | E18: Policy documents | F18: GRC Analyst | G18: Complete | H18: A. Khan | I18: 46307
A19: DD-11 | B19: 2. Security assurance | C19: External security posture checked (security rating or attack-surface scan; public breach history) | D19: All | E19: Scan output; news review | F19: Security Analyst | G19: Complete | H19: S. Ahmed | I19: 46308
A20: DD-12 | B20: 2. Security assurance | C20: Gaps logged with remediation plans and owners; critical gaps resolved or formally risk-accepted | D20: All | E20: Risk_Register entries | F20: GRC Analyst | G20: In Progress | J20: Critical gap AIG-02 open; remediation owner: Privacy Officer.
A21: DD-13 | B21: 3. Privacy & legal | C21: Data Processing Agreement executed (GDPR Art. 28, BAA or CCPA service-provider terms as applicable) | D21: All | E21: Signed DPA | F21: Privacy Officer | G21: In Progress
A22: DD-14 | B22: 3. Privacy & legal | C22: Subprocessor list, data residency and cross-border transfer mechanisms reviewed | D22: All | E22: Subprocessor list; SCCs | F22: Privacy Officer | G22: In Progress
A23: DD-15 | B23: 3. Privacy & legal | C23: Privacy impact assessment (DPIA) completed where personal data is processed at scale or at high risk | D23: All | E23: DPIA record | F23: Privacy Officer | G23: In Progress
A24: DD-16 | B24: 3. Privacy & legal | C24: Contract security schedule agreed: breach notification within 72 hours, audit rights, subcontractor flow-down, data return and deletion on exit | D24: All | E24: Contract clauses | F24: Legal | G24: In Progress
A25: DD-17 | B25: 3. Privacy & legal | C25: SLAs, limitation of liability and cyber insurance certificate reviewed | D25: All | E25: Contract; insurance certificate | F25: Legal / Procurement | G25: Not Started
A26: DD-18 | B26: 4. Resilience & exit | C26: BCP/DR summary and latest test results reviewed; RTO and RPO meet business requirements | D26: All | E26: DR test report | F26: IT Operations | G26: Not Started
A27: DD-19 | B27: 4. Resilience & exit | C27: Exit strategy and data portability plan documented (required for High and Critical vendors) | D27: All | E27: Exit plan | F27: Business Owner | G27: Not Started
A28: DD-20 | B28: 5. Cloud-specific | C28: Shared-responsibility matrix reviewed; customer-side controls (CUECs) mapped to internal owners | D28: Cloud | E28: Responsibility matrix | F28: Security Architect | G28: N/A | J28: Not applicable: SaaS API with no customer-managed infrastructure.
A29: DD-21 | B29: 5. Cloud-specific | C29: Hosting regions and backup regions approved against data residency requirements | D29: Cloud | E29: Region configuration | F29: Security Architect | G29: N/A | J29: Not applicable (see DD-20).
A30: DD-22 | B30: 5. Cloud-specific | C30: Customer-side configuration baseline defined (e.g., CIS Benchmarks) with posture monitoring before go-live | D30: Cloud | E30: Baseline; CSPM config | F30: Cloud Engineer | G30: N/A | J30: Not applicable (see DD-20).
A31: DD-23 | B31: 6. AI-specific | C31: AI use case, intended purpose and data categories documented; AI impact assessment completed (ISO/IEC 42001 Annex A.5) | D31: AI | E31: AI impact assessment | F31: AI Governance Lead | G31: Complete | H31: N. Raza | I31: 46314
A32: DD-24 | B32: 6. AI-specific | C32: Written confirmation that customer data, prompts and outputs are not used for model training; retention terms agreed (zero-retention option where available) | D32: AI | E32: Contract clause; vendor letter | F32: Privacy Officer | G32: Exception | H32: F. Iqbal | J32: Vendor retains prompts for 30 days and reserves the right to use them for model improvement. Contract amendment requested (see VR-004).
A33: DD-25 | B33: 6. AI-specific | C33: Model or system card reviewed (intended use, limitations, evaluation results, known risks) | D33: AI | E33: Model card | F33: Data Science Lead | G33: Complete | H33: N. Raza | I33: 46315
A34: DD-26 | B34: 6. AI-specific | C34: Vendor AI governance evidence reviewed (ISO/IEC 42001 certification or NIST AI RMF alignment; responsible AI policy) | D34: AI | E34: Certificate; policy | F34: AI Governance Lead | G34: In Progress
A35: DD-27 | B35: 6. AI-specific | C35: Output risk controls defined: human review, content filtering, prompt and output logging, staff acceptable-use rules | D35: AI | E35: Control design | F35: AI Governance Lead | G35: In Progress
A36: DD-28 | B36: 6. AI-specific | C36: AI security testing reviewed or planned (prompt injection, data leakage, jailbreak) | D36: AI | E36: Test results | F36: Security Analyst | G36: Not Started
A37: DD-29 | B37: 6. AI-specific | C37: Regulatory mapping completed (EU AI Act risk classification, sector rules) | D37: AI | E37: Regulatory mapping | F37: Legal / Compliance | G37: Not Started
A38: DD-30 | B38: 7. Decision & onboarding | C38: Residual risk calculated and recommendation recorded in Vendor_Register | D38: All | E38: Vendor_Register | F38: GRC Analyst | G38: Not Started
A39: DD-31 | B39: 7. Decision & onboarding | C39: Approval obtained from the authority required for the residual rating (see Approval_Workflow) | D39: All | E39: Signed approval record | F39: Approver | G39: Not Started
A40: DD-32 | B40: 7. Decision & onboarding | C40: Vendor onboarded: SSO and MFA configured, least-privilege roles assigned, logging integrated | D40: All | E40: Go-live checklist | F40: IT / Business Owner | G40: Not Started
A41: DD-33 | B41: 7. Decision & onboarding | C41: Monitoring schedule set and next review date recorded | D41: All | E41: Monitoring sheet | F41: GRC Analyst | G41: Not Started
A42: DD-34 | B42: 7. Decision & onboarding | C42: Contract and evidence pack archived in the vendor file | D42: All | E42: Evidence repository | F42: GRC Analyst | G42: Not Started
A44: Sample statuses shown for the fictional vendor V-002 (AI platform). Duplicate this sheet or reset statuses to 'Not Started' for each new vendor review; keep a signed copy in the vendor file.

Sheet Risk_Register
A1: Vendor Risk Register
A2: Individual third-party risks scored on a 5×5 likelihood × impact scale (see Methodology §6). Sample entries are fictional.
A5: Risk ID | B5: Vendor ID | C5: Vendor name | D5: Risk category | E5: Risk description | F5: Inherent likelihood | G5: Inherent impact | H5: Inherent score | I5: Inherent rating | J5: Existing controls | K5: Residual likelihood | L5: Residual impact | M5: Residual score | N5: Residual rating | O5: Treatment | P5: Treatment action | Q5: Risk owner | R5: Target date | S5: Status
A6: VR-001 | B6: V-001 | C6: =IF(B6="","",IFERROR(INDEX(Vendor_Register!$B$6:$B$15,MATCH(B6,Vendor_Register!$A$6:$A$15,0)),"Unknown vendor ID")) -> Stratus Cloud Infrastructure | D6: Availability / resilience | E6: Regional outage of the cloud provider causes extended downtime of production services. | F6: 3 | G6: 5 | H6: =IF(OR(F6="",G6=""),"",F6*G6) -> 15 | I6: =IF(H6="","",INDEX(Methodology!$A$55:$A$58,MATCH(H6,Methodology!$B$55:$B$58,1))) -> High | J6: Multi-AZ deployment; 99.95% SLA with service credits. | K6: 2 | L6: 4 | M6: =IF(OR(K6="",L6=""),"",K6*L6) -> 8 | N6: =IF(M6="","",INDEX(Methodology!$A$55:$A$58,MATCH(M6,Methodology!$B$55:$B$58,1))) -> Medium | O6: Mitigate | P6: Implement multi-region DR and perform an annual failover test. | Q6: Head of Infrastructure | R6: 46477 | S6: In Progress
A7: VR-002 | B7: V-001 | C7: =IF(B7="","",IFERROR(INDEX(Vendor_Register!$B$6:$B$15,MATCH(B7,Vendor_Register!$A$6:$A$15,0)),"Unknown vendor ID")) -> Stratus Cloud Infrastructure | D7: Concentration / lock-in | E7: Dependence on a single cloud provider limits ability to exit or negotiate. | F7: 3 | G7: 4 | H7: =IF(OR(F7="",G7=""),"",F7*G7) -> 12 | I7: =IF(H7="","",INDEX(Methodology!$A$55:$A$58,MATCH(H7,Methodology!$B$55:$B$58,1))) -> High | J7: Infrastructure-as-code; data export supported. | K7: 3 | L7: 3 | M7: =IF(OR(K7="",L7=""),"",K7*L7) -> 9 | N7: =IF(M7="","",INDEX(Methodology!$A$55:$A$58,MATCH(M7,Methodology!$B$55:$B$58,1))) -> Medium | O7: Mitigate | P7: Document an exit plan and test data portability annually. | Q7: Head of Infrastructure | R7: 46568 | S7: Open
A8: VR-003 | B8: V-001 | C8: =IF(B8="","",IFERROR(INDEX(Vendor_Register!$B$6:$B$15,MATCH(B8,Vendor_Register!$A$6:$A$15,0)),"Unknown vendor ID")) -> Stratus Cloud Infrastructure | D8: Information security / data breach | E8: Customer-side misconfiguration under the shared-responsibility model exposes stored data. | F8: 3 | G8: 5 | H8: =IF(OR(F8="",G8=""),"",F8*G8) -> 15 | I8: =IF(H8="","",INDEX(Methodology!$A$55:$A$58,MATCH(H8,Methodology!$B$55:$B$58,1))) -> High | J8: Guardrail policies; peer-reviewed infrastructure changes. | K8: 2 | L8: 4 | M8: =IF(OR(K8="",L8=""),"",K8*L8) -> 8 | N8: =IF(M8="","",INDEX(Methodology!$A$55:$A$58,MATCH(M8,Methodology!$B$55:$B$58,1))) -> Medium | O8: Mitigate | P8: Deploy CSPM with automated alerting on public exposure. | Q8: Cloud Security Lead | R8: 46371 | S8: In Progress
A9: VR-004 | B9: V-002 | C9: =IF(B9="","",IFERROR(INDEX(Vendor_Register!$B$6:$B$15,MATCH(B9,Vendor_Register!$A$6:$A$15,0)),"Unknown vendor ID")) -> NimbusAI Language Platform | D9: AI model & governance | E9: Customer prompts and data are retained and may be used to train vendor models. | F9: 4 | G9: 5 | H9: =IF(OR(F9="",G9=""),"",F9*G9) -> 20 | I9: =IF(H9="","",INDEX(Methodology!$A$55:$A$58,MATCH(H9,Methodology!$B$55:$B$58,1))) -> Critical | J9: None contractual; internal policy prohibits sensitive data in prompts. | K9: 2 | L9: 5 | M9: =IF(OR(K9="",L9=""),"",K9*L9) -> 10 | N9: =IF(M9="","",INDEX(Methodology!$A$55:$A$58,MATCH(M9,Methodology!$B$55:$B$58,1))) -> High | O9: Mitigate | P9: Negotiate zero-retention and no-training clauses in the DPA; block go-live until signed. | Q9: Privacy Officer | R9: 46357 | S9: In Progress
A10: VR-005 | B10: V-002 | C10: =IF(B10="","",IFERROR(INDEX(Vendor_Register!$B$6:$B$15,MATCH(B10,Vendor_Register!$A$6:$A$15,0)),"Unknown vendor ID")) -> NimbusAI Language Platform | D10: AI model & governance | E10: Inaccurate or fabricated outputs mislead customers or influence business decisions. | F10: 4 | G10: 3 | H10: =IF(OR(F10="",G10=""),"",F10*G10) -> 12 | I10: =IF(H10="","",INDEX(Methodology!$A$55:$A$58,MATCH(H10,Methodology!$B$55:$B$58,1))) -> High | J10: Human review of high-impact responses. | K10: 3 | L10: 3 | M10: =IF(OR(K10="",L10=""),"",K10*L10) -> 9 | N10: =IF(M10="","",INDEX(Methodology!$A$55:$A$58,MATCH(M10,Methodology!$B$55:$B$58,1))) -> Medium | O10: Mitigate | P10: Add output confidence thresholds, response logging and a monthly quality review. | Q10: Director of Customer Support | R10: 46418 | S10: Open
A11: VR-006 | B11: V-002 | C11: =IF(B11="","",IFERROR(INDEX(Vendor_Register!$B$6:$B$15,MATCH(B11,Vendor_Register!$A$6:$A$15,0)),"Unknown vendor ID")) -> NimbusAI Language Platform | D11: Information security / data breach | E11: Prompt injection through integrations leads to data exfiltration. | F11: 3 | G11: 4 | H11: =IF(OR(F11="",G11=""),"",F11*G11) -> 12 | I11: =IF(H11="","",INDEX(Methodology!$A$55:$A$58,MATCH(H11,Methodology!$B$55:$B$58,1))) -> High | J11: API keys scoped per environment. | K11: 2 | L11: 4 | M11: =IF(OR(K11="",L11=""),"",K11*L11) -> 8 | N11: =IF(M11="","",INDEX(Methodology!$A$55:$A$58,MATCH(M11,Methodology!$B$55:$B$58,1))) -> Medium | O11: Mitigate | P11: Run an internal red-team test and add input/output filtering. | Q11: Security Analyst | R11: 46402 | S11: Open
A12: VR-007 | B12: V-003 | C12: =IF(B12="","",IFERROR(INDEX(Vendor_Register!$B$6:$B$15,MATCH(B12,Vendor_Register!$A$6:$A$15,0)),"Unknown vendor ID")) -> Orbit CRM Suite | D12: Information security / data breach | E12: Weak privileged access control and log retention at the vendor delay breach detection. | F12: 3 | G12: 4 | H12: =IF(OR(F12="",G12=""),"",F12*G12) -> 12 | I12: =IF(H12="","",INDEX(Methodology!$A$55:$A$58,MATCH(H12,Methodology!$B$55:$B$58,1))) -> High | J12: SSO and MFA enforced for our users. | K12: 3 | L12: 3 | M12: =IF(OR(K12="",L12=""),"",K12*L12) -> 9 | N12: =IF(M12="","",INDEX(Methodology!$A$55:$A$58,MATCH(M12,Methodology!$B$55:$B$58,1))) -> Medium | O12: Mitigate | P12: Require PAM and 12-month log retention as a contract remediation item. | Q12: VP Sales | R12: 46477 | S12: In Progress
A13: VR-008 | B13: V-003 | C13: =IF(B13="","",IFERROR(INDEX(Vendor_Register!$B$6:$B$15,MATCH(B13,Vendor_Register!$A$6:$A$15,0)),"Unknown vendor ID")) -> Orbit CRM Suite | D13: Availability / resilience | E13: No tested disaster recovery; extended outage disrupts the sales pipeline. | F13: 2 | G13: 4 | H13: =IF(OR(F13="",G13=""),"",F13*G13) -> 8 | I13: =IF(H13="","",INDEX(Methodology!$A$55:$A$58,MATCH(H13,Methodology!$B$55:$B$58,1))) -> Medium | J13: Vendor SLA of 99.9%; weekly CRM export to our storage. | K13: 2 | L13: 3 | M13: =IF(OR(K13="",L13=""),"",K13*L13) -> 6 | N13: =IF(M13="","",INDEX(Methodology!$A$55:$A$58,MATCH(M13,Methodology!$B$55:$B$58,1))) -> Medium | O13: Mitigate | P13: Require annual DR test evidence at renewal. | Q13: VP Sales | R13: 46630 | S13: Open
A14: VR-009 | B14: V-004 | C14: =IF(B14="","",IFERROR(INDEX(Vendor_Register!$B$6:$B$15,MATCH(B14,Vendor_Register!$A$6:$A$15,0)),"Unknown vendor ID")) -> InsightML Analytics | D14: AI model & governance | E14: Model drift or bias degrades churn predictions used in business planning. | F14: 3 | G14: 3 | H14: =IF(OR(F14="",G14=""),"",F14*G14) -> 9 | I14: =IF(H14="","",INDEX(Methodology!$A$55:$A$58,MATCH(H14,Methodology!$B$55:$B$58,1))) -> Medium | J14: Quarterly manual comparison against actuals. | K14: 2 | L14: 3 | M14: =IF(OR(K14="",L14=""),"",K14*L14) -> 6 | N14: =IF(M14="","",INDEX(Methodology!$A$55:$A$58,MATCH(M14,Methodology!$B$55:$B$58,1))) -> Medium | O14: Mitigate | P14: Obtain model performance reports and set drift thresholds. | Q14: Head of Data Science | R14: 46477 | S14: Open
A15: VR-010 | B15: V-004 | C15: =IF(B15="","",IFERROR(INDEX(Vendor_Register!$B$6:$B$15,MATCH(B15,Vendor_Register!$A$6:$A$15,0)),"Unknown vendor ID")) -> InsightML Analytics | D15: Regulatory & compliance | E15: Vendor does not meet emerging AI regulation obligations (e.g., EU AI Act transparency duties). | F15: 3 | G15: 3 | H15: =IF(OR(F15="",G15=""),"",F15*G15) -> 9 | I15: =IF(H15="","",INDEX(Methodology!$A$55:$A$58,MATCH(H15,Methodology!$B$55:$B$58,1))) -> Medium | J15: Contract requires legal compliance. | K15: 2 | L15: 3 | M15: =IF(OR(K15="",L15=""),"",K15*L15) -> 6 | N15: =IF(M15="","",INDEX(Methodology!$A$55:$A$58,MATCH(M15,Methodology!$B$55:$B$58,1))) -> Medium | O15: Mitigate | P15: Complete AI regulatory mapping and request vendor roadmap. | Q15: Legal / Compliance | R15: 46507 | S15: Open
A16: VR-011 | B16: V-005 | C16: =IF(B16="","",IFERROR(INDEX(Vendor_Register!$B$6:$B$15,MATCH(B16,Vendor_Register!$A$6:$A$15,0)),"Unknown vendor ID")) -> Cirrus Backup & Recovery | D16: Privacy & data protection | E16: Backup copies are stored outside approved regions. | F16: 2 | G16: 4 | H16: =IF(OR(F16="",G16=""),"",F16*G16) -> 8 | I16: =IF(H16="","",INDEX(Methodology!$A$55:$A$58,MATCH(H16,Methodology!$B$55:$B$58,1))) -> Medium | J16: Region configuration locked to approved zones. | K16: 1 | L16: 4 | M16: =IF(OR(K16="",L16=""),"",K16*L16) -> 4 | N16: =IF(M16="","",INDEX(Methodology!$A$55:$A$58,MATCH(M16,Methodology!$B$55:$B$58,1))) -> Low | O16: Accept | P16: Accept with annual verification of backup region settings. | Q16: IT Operations Manager | R16: 46538 | S16: Accepted
A17: VR-012 | B17: V-006 | C17: =IF(B17="","",IFERROR(INDEX(Vendor_Register!$B$6:$B$15,MATCH(B17,Vendor_Register!$A$6:$A$15,0)),"Unknown vendor ID")) -> Brightleaf Survey Tool | D17: Contractual & commercial | E17: Contract lacks a defined breach notification timeline. | F17: 2 | G17: 3 | H17: =IF(OR(F17="",G17=""),"",F17*G17) -> 6 | I17: =IF(H17="","",INDEX(Methodology!$A$55:$A$58,MATCH(H17,Methodology!$B$55:$B$58,1))) -> Medium | J17: Survey data contains limited personal data. | K17: 2 | L17: 2 | M17: =IF(OR(K17="",L17=""),"",K17*L17) -> 4 | N17: =IF(M17="","",INDEX(Methodology!$A$55:$A$58,MATCH(M17,Methodology!$B$55:$B$58,1))) -> Low | O17: Accept | P17: Request breach notification clause at the December 2026 renewal. | Q17: Marketing Manager | R17: 46387 | S17: Accepted
C18: =IF(B18="","",IFERROR(INDEX(Vendor_Register!$B$6:$B$15,MATCH(B18,Vendor_Register!$A$6:$A$15,0)),"Unknown vendor ID")) | H18: =IF(OR(F18="",G18=""),"",F18*G18) | I18: =IF(H18="","",INDEX(Methodology!$A$55:$A$58,MATCH(H18,Methodology!$B$55:$B$58,1))) | M18: =IF(OR(K18="",L18=""),"",K18*L18) | N18: =IF(M18="","",INDEX(Methodology!$A$55:$A$58,MATCH(M18,Methodology!$B$55:$B$58,1)))
C19: =IF(B19="","",IFERROR(INDEX(Vendor_Register!$B$6:$B$15,MATCH(B19,Vendor_Register!$A$6:$A$15,0)),"Unknown vendor ID")) | H19: =IF(OR(F19="",G19=""),"",F19*G19) | I19: =IF(H19="","",INDEX(Methodology!$A$55:$A$58,MATCH(H19,Methodology!$B$55:$B$58,1))) | M19: =IF(OR(K19="",L19=""),"",K19*L19) | N19: =IF(M19="","",INDEX(Methodology!$A$55:$A$58,MATCH(M19,Methodology!$B$55:$B$58,1)))
C20: =IF(B20="","",IFERROR(INDEX(Vendor_Register!$B$6:$B$15,MATCH(B20,Vendor_Register!$A$6:$A$15,0)),"Unknown vendor ID")) | H20: =IF(OR(F20="",G20=""),"",F20*G20) | I20: =IF(H20="","",INDEX(Methodology!$A$55:$A$58,MATCH(H20,Methodology!$B$55:$B$58,1))) | M20: =IF(OR(K20="",L20=""),"",K20*L20) | N20: =IF(M20="","",INDEX(Methodology!$A$55:$A$58,MATCH(M20,Methodology!$B$55:$B$58,1)))
C21: =IF(B21="","",IFERROR(INDEX(Vendor_Register!$B$6:$B$15,MATCH(B21,Vendor_Register!$A$6:$A$15,0)),"Unknown vendor ID")) | H21: =IF(OR(F21="",G21=""),"",F21*G21) | I21: =IF(H21="","",INDEX(Methodology!$A$55:$A$58,MATCH(H21,Methodology!$B$55:$B$58,1))) | M21: =IF(OR(K21="",L21=""),"",K21*L21) | N21: =IF(M21="","",INDEX(Methodology!$A$55:$A$58,MATCH(M21,Methodology!$B$55:$B$58,1)))
C22: =IF(B22="","",IFERROR(INDEX(Vendor_Register!$B$6:$B$15,MATCH(B22,Vendor_Register!$A$6:$A$15,0)),"Unknown vendor ID")) | H22: =IF(OR(F22="",G22=""),"",F22*G22) | I22: =IF(H22="","",INDEX(Methodology!$A$55:$A$58,MATCH(H22,Methodology!$B$55:$B$58,1))) | M22: =IF(OR(K22="",L22=""),"",K22*L22) | N22: =IF(M22="","",INDEX(Methodology!$A$55:$A$58,MATCH(M22,Methodology!$B$55:$B$58,1)))
C23: =IF(B23="","",IFERROR(INDEX(Vendor_Register!$B$6:$B$15,MATCH(B23,Vendor_Register!$A$6:$A$15,0)),"Unknown vendor ID")) | H23: =IF(OR(F23="",G23=""),"",F23*G23) | I23: =IF(H23="","",INDEX(Methodology!$A$55:$A$58,MATCH(H23,Methodology!$B$55:$B$58,1))) | M23: =IF(OR(K23="",L23=""),"",K23*L23) | N23: =IF(M23="","",INDEX(Methodology!$A$55:$A$58,MATCH(M23,Methodology!$B$55:$B$58,1)))
C24: =IF(B24="","",IFERROR(INDEX(Vendor_Register!$B$6:$B$15,MATCH(B24,Vendor_Register!$A$6:$A$15,0)),"Unknown vendor ID")) | H24: =IF(OR(F24="",G24=""),"",F24*G24) | I24: =IF(H24="","",INDEX(Methodology!$A$55:$A$58,MATCH(H24,Methodology!$B$55:$B$58,1))) | M24: =IF(OR(K24="",L24=""),"",K24*L24) | N24: =IF(M24="","",INDEX(Methodology!$A$55:$A$58,MATCH(M24,Methodology!$B$55:$B$58,1)))
C25: =IF(B25="","",IFERROR(INDEX(Vendor_Register!$B$6:$B$15,MATCH(B25,Vendor_Register!$A$6:$A$15,0)),"Unknown vendor ID")) | H25: =IF(OR(F25="",G25=""),"",F25*G25) | I25: =IF(H25="","",INDEX(Methodology!$A$55:$A$58,MATCH(H25,Methodology!$B$55:$B$58,1))) | M25: =IF(OR(K25="",L25=""),"",K25*L25) | N25: =IF(M25="","",INDEX(Methodology!$A$55:$A$58,MATCH(M25,Methodology!$B$55:$B$58,1)))
C26: =IF(B26="","",IFERROR(INDEX(Vendor_Register!$B$6:$B$15,MATCH(B26,Vendor_Register!$A$6:$A$15,0)),"Unknown vendor ID")) | H26: =IF(OR(F26="",G26=""),"",F26*G26) | I26: =IF(H26="","",INDEX(Methodology!$A$55:$A$58,MATCH(H26,Methodology!$B$55:$B$58,1))) | M26: =IF(OR(K26="",L26=""),"",K26*L26) | N26: =IF(M26="","",INDEX(Methodology!$A$55:$A$58,MATCH(M26,Methodology!$B$55:$B$58,1)))
C27: =IF(B27="","",IFERROR(INDEX(Vendor_Register!$B$6:$B$15,MATCH(B27,Vendor_Register!$A$6:$A$15,0)),"Unknown vendor ID")) | H27: =IF(OR(F27="",G27=""),"",F27*G27) | I27: =IF(H27="","",INDEX(Methodology!$A$55:$A$58,MATCH(H27,Methodology!$B$55:$B$58,1))) | M27: =IF(OR(K27="",L27=""),"",K27*L27) | N27: =IF(M27="","",INDEX(Methodology!$A$55:$A$58,MATCH(M27,Methodology!$B$55:$B$58,1)))
C28: =IF(B28="","",IFERROR(INDEX(Vendor_Register!$B$6:$B$15,MATCH(B28,Vendor_Register!$A$6:$A$15,0)),"Unknown vendor ID")) | H28: =IF(OR(F28="",G28=""),"",F28*G28) | I28: =IF(H28="","",INDEX(Methodology!$A$55:$A$58,MATCH(H28,Methodology!$B$55:$B$58,1))) | M28: =IF(OR(K28="",L28=""),"",K28*L28) | N28: =IF(M28="","",INDEX(Methodology!$A$55:$A$58,MATCH(M28,Methodology!$B$55:$B$58,1)))
C29: =IF(B29="","",IFERROR(INDEX(Vendor_Register!$B$6:$B$15,MATCH(B29,Vendor_Register!$A$6:$A$15,0)),"Unknown vendor ID")) | H29: =IF(OR(F29="",G29=""),"",F29*G29) | I29: =IF(H29="","",INDEX(Methodology!$A$55:$A$58,MATCH(H29,Methodology!$B$55:$B$58,1))) | M29: =IF(OR(K29="",L29=""),"",K29*L29) | N29: =IF(M29="","",INDEX(Methodology!$A$55:$A$58,MATCH(M29,Methodology!$B$55:$B$58,1)))
... C35: =IF(B35="","",IFERROR(INDEX(Vendor_Register!$B$6:$B$15,MATCH(B35,Vendor_Register!$A$6:$A$15,0)),"Unknown vendor ID")) | H35: =IF(OR(F35="",G35=""),"",F35*G35) | I35: =IF(H35="","",INDEX(Methodology!$A$55:$A$58,MATCH(H35,Methodology!$B$55:$B$58,1))) | M35: =IF(OR(K35="",L35=""),"",K35*L35) | N35: =IF(M35="","",INDEX(Methodology!$A$55:$A$58,MATCH(M35,Methodology!$B$55:$B$58,1)))

Sheet Approval_Workflow
A1: Security Review & Approval Workflow
A2: Ten-stage lifecycle from request to offboarding. SLAs are in business days and exclude time waiting on the vendor.
A5: Step | B5: Stage | C5: Key activities | D5: Owner | E5: Inputs | F5: Outputs / evidence | G5: SLA (business days) | H5: Decision gate
A6: 1 | B6: Request & business case | C6: Business owner submits the vendor intake form (service, data types, users, alternatives considered). GRC checks for an existing vendor or duplicate and logs a Vendor ID. | D6: Business Owner / GRC Analyst | E6: Intake request | F6: Vendor_Register entry | G6: 2 | H6: Intake complete; no duplicate vendor
A7: 2 | B7: Inherent risk triage | C7: Score the six inherent risk factors, derive the inherent rating and set the assessment depth (Low: streamlined; Medium and above: full). | D7: GRC Analyst | E7: Intake form; data-flow description | F7: Inherent score and rating; assessment scope | G7: 2 | H7: Tier assigned and recorded
A8: 3 | B8: Due diligence & questionnaire | C8: Issue the questionnaire; collect SOC 2 or ISO certificates, penetration test summary, policies and subprocessor list; work through the Due_Diligence checklist. | D8: GRC Analyst / Procurement | E8: Questionnaire; evidence request list | F8: Completed questionnaire; evidence pack | G8: 10 | H8: Evidence received and complete
A9: 4 | B9: Security review | C9: Validate answers against evidence, review architecture and integrations, score control effectiveness and log gaps with severity. | D9: Security Analyst / Architect | E9: Questionnaire; certificates; architecture | F9: Assessment_Results; findings list | G9: 5 | H9: Critical gaps identified and logged
A10: 5 | B10: Privacy & legal review | C10: Review DPA, data residency, cross-border transfers, subprocessors, security schedule, liability and insurance. | D10: Privacy Officer / Legal | E10: Draft contract; DPA; subprocessor list | F10: Contract mark-up; DPIA where required | G10: 5 | H10: DPA executed or exception approved
A11: 6 | B11: AI governance review (AI vendors) | C11: Review AI impact assessment, data-use restrictions, model documentation, AI security testing and regulatory classification (ISO/IEC 42001, NIST AI RMF, EU AI Act). | D11: AI Governance Lead / Data Science | E11: Model card; AI impact assessment | F11: AI governance sign-off | G11: 5 | H11: AI use case approved by AI governance forum
A12: 7 | B12: Residual risk & recommendation | C12: Calculate residual risk, register risks in Risk_Register with treatment plans and issue a recommendation. | D12: GRC Analyst | E12: Findings; control effectiveness | F12: Residual rating; risk entries; recommendation | G12: 3 | H12: Recommendation issued
A13: 8 | B13: Approval decision | C13: Approver selected from the authority matrix below decides: approve, conditionally approve (with dated remediation plan) or reject. | D13: Approver (see matrix) | E13: Recommendation pack | F13: Signed decision record | G13: 5 | H13: Decision recorded
A14: 9 | B14: Contracting & onboarding | C14: Execute contract with the security schedule; configure SSO and MFA, least-privilege roles and log forwarding; set the monitoring schedule. | D14: Procurement / IT / Business Owner | E14: Approved decision; final contract | F14: Go-live checklist; monitoring schedule entry | G14: 10 | H14: Go-live checklist signed
A15: 10 | B15: Monitoring & offboarding | C15: Monitor per the Monitoring sheet; reassess on schedule or on trigger events. At exit, revoke access and obtain a data return or deletion certificate. | D15: GRC Analyst / Business Owner | E15: Monitoring schedule; trigger events | F15: Review records; offboarding certificate | G15: Per schedule | H15: Periodic review complete; exit verified
A18: Approval authority matrix (by residual risk rating)
A19: Residual rating | B19: Required approver | C19: Conditions | D19: Maximum approval validity
A20: Low | B20: Business Owner + GRC Analyst | C20: Standard terms; no open critical gaps. | D20: Until next scheduled review
A21: Medium | B21: Business Owner + Information Security Manager | C21: Open findings tracked in Risk_Register with owners and dates. | D21: Until next scheduled review
A22: High | B22: Information Security Manager + Privacy/Legal + Head of Business Unit | C22: Conditional approval; remediation plan with dated milestones; exit plan on file. | D22: 12 months or until milestones missed
A23: Critical | B23: CISO + Risk Committee (executive risk acceptance) | C23: Formal risk acceptance memo; enhanced monitoring; tested exit plan. | D23: 12 months; quarterly reporting to committee
A25: Exception & escalation rules
A26: 1. Any critical control gap (a 'No' on a Critical control) must be remediated or formally risk-accepted by the approver for the Critical tier before go-live.
A27: 2. AI vendors require AI governance review (step 6) in addition to the standard approver, regardless of residual rating.
A28: 3. Risk acceptances are time-bound (maximum 12 months), recorded in Risk_Register with status 'Accepted' and re-approved at expiry.
A29: 4. Business units may not sign contracts or share data with a vendor before step 8 is complete; emergency requests need CISO written approval.
A30: 5. Rejected vendors are recorded with the rationale and may only be resubmitted when the blocking issue is resolved.

Sheet Monitoring
A1: Ongoing Monitoring Schedule
A2: Cadence is driven by the inherent rating. Section B calculates each vendor's next review dates; section C lists event-driven triggers.
A3: A. Monitoring cadence by tier
A4: Activity | B4: Critical | C4: High | D4: Medium | E4: Low | F4: Owner | G4: Method
A5: Full risk reassessment (months) | B5: =Methodology!$D$23 -> 12 | C5: =Methodology!$D$22 -> 18 | D5: =Methodology!$D$21 -> 24 | E5: =Methodology!$D$20 -> 36 | F5: GRC Analyst | G5: Refreshed questionnaire, evidence review, rescoring
A6: Interim check-in (months; 0 = at renewal) | B6: =Methodology!$E$23 -> 3 | C6: =Methodology!$E$22 -> 6 | D6: =Methodology!$E$21 -> 12 | E6: =Methodology!$E$20 -> 0 | F6: GRC Analyst | G6: Attestation of no material change; open findings review
A7: Security posture and breach monitoring | B7: Continuous alerts | C7: Monthly | D7: Quarterly | E7: Annually | F7: Security Analyst | G7: Security ratings, attack-surface scan, breach and adverse-media alerts
A8: Certification / attestation validity | B8: Each report cycle | C8: Each report cycle | D8: Annually | E8: At renewal | F8: GRC Analyst | G8: SOC 2 / ISO certificate expiry and bridge-letter review
A9: Remediation tracking of open findings | B9: Monthly | C9: Monthly | D9: Quarterly | E9: At review | F9: GRC Analyst | G9: Risk_Register status review
A10: SLA and service performance review | B10: Quarterly | C10: Quarterly | D10: Semi-annually | E10: Annually | F10: Business Owner | G10: SLA reports, incident log, service review meeting
A11: Access review of vendor accounts in our environment | B11: Quarterly | C11: Quarterly | D11: Semi-annually | E11: Annually | F11: IT / Business Owner | G11: Access recertification
A12: Subprocessor and ownership change review | B12: On notice | C12: On notice | D12: On notice | E12: On notice | F12: Privacy Officer | G12: Vendor notification; contract clause
A13: AI model / version change review (AI vendors) | B13: Each major release | C13: Each major release | D13: Quarterly | E13: At renewal | F13: AI Governance Lead | G13: Release notes, model card update, re-test of key controls
A14: Contract renewal review | B14: 180 days before | C14: 180 days before | D14: 120 days before | E14: 90 days before | F14: Procurement | G14: Performance, risk and exit-option review
A17: B. Vendor monitoring calendar (calculated)
A18: Vendor ID | B18: Vendor name | C18: Inherent rating | D18: Last assessment | E18: Next full reassessment | F18: Interim interval (months) | G18: Next interim check | H18: Attestation expiry (input) | I18: Attestation status | J18: Contract renewal | K18: Renewal review date | L18: Overall status
A19: =IF(Vendor_Register!A6="","",Vendor_Register!A6) -> V-001 | B19: =IF($A19="","",Vendor_Register!B6) -> Stratus Cloud Infrastructure | C19: =IF($A19="","",Vendor_Register!M6) -> Critical | D19: =IF(OR($A19="",Vendor_Register!U6=""),"",Vendor_Register!U6) -> 46093 | E19: =IF($A19="","",Vendor_Register!W6) -> 46458 | F19: =IF($A19="","",INDEX(Methodology!$E$20:$E$23,MATCH(C19,Methodology!$A$20:$A$23,0))) -> 3 | G19: =IF(OR($A19="",D19=""),"",IF(F19=0,"At renewal",EDATE(D19,F19*(INT(((YEAR(Methodology!$B$4)-YEAR(D19))*12+MONTH(Methodology!$B$4)-MONTH(D19))/F19)+1)))) -> 46368 | H19: 46446 | I19: =IF($A19="","",IF(H19="","Not recorded",IF(H19<Methodology!$B$4,"Expired",IF(H19-Methodology!$B$4<=90,"Expiring within 90 days","Valid")))) -> Valid | J19: =IF(OR($A19="",Vendor_Register!Y6=""),"",Vendor_Register!Y6) -> 46568 | K19: =IF(J19="","",J19-IF(C19="Critical",180,IF(C19="High",180,IF(C19="Medium",120,90)))) -> 46388 | L19: =IF($A19="","",IF(E19="","Not yet assessed",IF(E19<Methodology!$B$4,"Reassessment overdue",IF(I19="Expired","Attestation expired",IF(OR(I19="Expiring within 90 days",E19-Methodology!$B$4<=90),"Action due within 90 days","On track"))))) -> On track
A20: =IF(Vendor_Register!A7="","",Vendor_Register!A7) -> V-002 | B20: =IF($A20="","",Vendor_Register!B7) -> NimbusAI Language Platform | C20: =IF($A20="","",Vendor_Register!M7) -> High | D20: =IF(OR($A20="",Vendor_Register!U7=""),"",Vendor_Register!U7) | E20: =IF($A20="","",Vendor_Register!W7) | F20: =IF($A20="","",INDEX(Methodology!$E$20:$E$23,MATCH(C20,Methodology!$A$20:$A$23,0))) -> 6 | G20: =IF(OR($A20="",D20=""),"",IF(F20=0,"At renewal",EDATE(D20,F20*(INT(((YEAR(Methodology!$B$4)-YEAR(D20))*12+MONTH(Methodology!$B$4)-MONTH(D20))/F20)+1)))) | H20: 46371 | I20: =IF($A20="","",IF(H20="","Not recorded",IF(H20<Methodology!$B$4,"Expired",IF(H20-Methodology!$B$4<=90,"Expiring within 90 days","Valid")))) -> Expiring within 90 days | J20: =IF(OR($A20="",Vendor_Register!Y7=""),"",Vendor_Register!Y7) -> 46675 | K20: =IF(J20="","",J20-IF(C20="Critical",180,IF(C20="High",180,IF(C20="Medium",120,90)))) -> 46495 | L20: =IF($A20="","",IF(E20="","Not yet assessed",IF(E20<Methodology!$B$4,"Reassessment overdue",IF(I20="Expired","Attestation expired",IF(OR(I20="Expiring within 90 days",E20-Methodology!$B$4<=90),"Action due within 90 days","On track"))))) -> Not yet assessed
A21: =IF(Vendor_Register!A8="","",Vendor_Register!A8) -> V-003 | B21: =IF($A21="","",Vendor_Register!B8) -> Orbit CRM Suite | C21: =IF($A21="","",Vendor_Register!M8) -> High | D21: =IF(OR($A21="",Vendor_Register!U8=""),"",Vendor_Register!U8) -> 45920 | E21: =IF($A21="","",Vendor_Register!W8) -> 46466 | F21: =IF($A21="","",INDEX(Methodology!$E$20:$E$23,MATCH(C21,Methodology!$A$20:$A$23,0))) -> 6 | G21: =IF(OR($A21="",D21=""),"",IF(F21=0,"At renewal",EDATE(D21,F21*(INT(((YEAR(Methodology!$B$4)-YEAR(D21))*12+MONTH(Methodology!$B$4)-MONTH(D21))/F21)+1)))) -> 46466 | H21: 46265 | I21: =IF($A21="","",IF(H21="","Not recorded",IF(H21<Methodology!$B$4,"Expired",IF(H21-Methodology!$B$4<=90,"Expiring within 90 days","Valid")))) -> Expired | J21: =IF(OR($A21="",Vendor_Register!Y8=""),"",Vendor_Register!Y8) -> 46630 | K21: =IF(J21="","",J21-IF(C21="Critical",180,IF(C21="High",180,IF(C21="Medium",120,90)))) -> 46450 | L21: =IF($A21="","",IF(E21="","Not yet assessed",IF(E21<Methodology!$B$4,"Reassessment overdue",IF(I21="Expired","Attestation expired",IF(OR(I21="Expiring within 90 days",E21-Methodology!$B$4<=90),"Action due within 90 days","On track"))))) -> Attestation expired
A22: =IF(Vendor_Register!A9="","",Vendor_Register!A9) -> V-004 | B22: =IF($A22="","",Vendor_Register!B9) -> InsightML Analytics | C22: =IF($A22="","",Vendor_Register!M9) -> Medium | D22: =IF(OR($A22="",Vendor_Register!U9=""),"",Vendor_Register!U9) -> 45519 | E22: =IF($A22="","",Vendor_Register!W9) -> 46249 | F22: =IF($A22="","",INDEX(Methodology!$E$20:$E$23,MATCH(C22,Methodology!$A$20:$A$23,0))) -> 12 | G22: =IF(OR($A22="",D22=""),"",IF(F22=0,"At renewal",EDATE(D22,F22*(INT(((YEAR(Methodology!$B$4)-YEAR(D22))*12+MONTH(Methodology!$B$4)-MONTH(D22))/F22)+1)))) -> 46614 | H22: 46538 | I22: =IF($A22="","",IF(H22="","Not recorded",IF(H22<Methodology!$B$4,"Expired",IF(H22-Methodology!$B$4<=90,"Expiring within 90 days","Valid")))) -> Valid | J22: =IF(OR($A22="",Vendor_Register!Y9=""),"",Vendor_Register!Y9) -> 46507 | K22: =IF(J22="","",J22-IF(C22="Critical",180,IF(C22="High",180,IF(C22="Medium",120,90)))) -> 46387 | L22: =IF($A22="","",IF(E22="","Not yet assessed",IF(E22<Methodology!$B$4,"Reassessment overdue",IF(I22="Expired","Attestation expired",IF(OR(I22="Expiring within 90 days",E22-Methodology!$B$4<=90),"Action due within 90 days","On track"))))) -> Reassessment overdue
A23: =IF(Vendor_Register!A10="","",Vendor_Register!A10) -> V-005 | B23: =IF($A23="","",Vendor_Register!B10) -> Cirrus Backup & Recovery | C23: =IF($A23="","",Vendor_Register!M10) -> High | D23: =IF(OR($A23="",Vendor_Register!U10=""),"",Vendor_Register!U10) -> 45782 | E23: =IF($A23="","",Vendor_Register!W10) -> 46331 | F23: =IF($A23="","",INDEX(Methodology!$E$20:$E$23,MATCH(C23,Methodology!$A$20:$A$23,0))) -> 6 | G23: =IF(OR($A23="",D23=""),"",IF(F23=0,"At renewal",EDATE(D23,F23*(INT(((YEAR(Methodology!$B$4)-YEAR(D23))*12+MONTH(Methodology!$B$4)-MONTH(D23))/F23)+1)))) -> 46331 | H23: 46407 | I23: =IF($A23="","",IF(H23="","Not recorded",IF(H23<Methodology!$B$4,"Expired",IF(H23-Methodology!$B$4<=90,"Expiring within 90 days","Valid")))) -> Expiring within 90 days | J23: =IF(OR($A23="",Vendor_Register!Y10=""),"",Vendor_Register!Y10) -> 46538 | K23: =IF(J23="","",J23-IF(C23="Critical",180,IF(C23="High",180,IF(C23="Medium",120,90)))) -> 46358 | L23: =IF($A23="","",IF(E23="","Not yet assessed",IF(E23<Methodology!$B$4,"Reassessment overdue",IF(I23="Expired","Attestation expired",IF(OR(I23="Expiring within 90 days",E23-Methodology!$B$4<=90),"Action due within 90 days","On track"))))) -> Action due within 90 days
A24: =IF(Vendor_Register!A11="","",Vendor_Register!A11) -> V-006 | B24: =IF($A24="","",Vendor_Register!B11) -> Brightleaf Survey Tool | C24: =IF($A24="","",Vendor_Register!M11) -> Low | D24: =IF(OR($A24="",Vendor_Register!U11=""),"",Vendor_Register!U11) -> 45323 | E24: =IF($A24="","",Vendor_Register!W11) -> 46419 | F24: =IF($A24="","",INDEX(Methodology!$E$20:$E$23,MATCH(C24,Methodology!$A$20:$A$23,0))) -> 0 | G24: =IF(OR($A24="",D24=""),"",IF(F24=0,"At renewal",EDATE(D24,F24*(INT(((YEAR(Methodology!$B$4)-YEAR(D24))*12+MONTH(Methodology!$B$4)-MONTH(D24))/F24)+1)))) -> At renewal | I24: =IF($A24="","",IF(H24="","Not recorded",IF(H24<Methodology!$B$4,"Expired",IF(H24-Methodology!$B$4<=90,"Expiring within 90 days","Valid")))) -> Not recorded | J24: =IF(OR($A24="",Vendor_Register!Y11=""),"",Vendor_Register!Y11) -> 46477 | K24: =IF(J24="","",J24-IF(C24="Critical",180,IF(C24="High",180,IF(C24="Medium",120,90)))) -> 46387 | L24: =IF($A24="","",IF(E24="","Not yet assessed",IF(E24<Methodology!$B$4,"Reassessment overdue",IF(I24="Expired","Attestation expired",IF(OR(I24="Expiring within 90 days",E24-Methodology!$B$4<=90),"Action due within 90 days","On track"))))) -> On track
A25: =IF(Vendor_Register!A12="","",Vendor_Register!A12) | B25: =IF($A25="","",Vendor_Register!B12) | C25: =IF($A25="","",Vendor_Register!M12) | D25: =IF(OR($A25="",Vendor_Register!U12=""),"",Vendor_Register!U12) | E25: =IF($A25="","",Vendor_Register!W12) | F25: =IF($A25="","",INDEX(Methodology!$E$20:$E$23,MATCH(C25,Methodology!$A$20:$A$23,0))) | G25: =IF(OR($A25="",D25=""),"",IF(F25=0,"At renewal",EDATE(D25,F25*(INT(((YEAR(Methodology!$B$4)-YEAR(D25))*12+MONTH(Methodology!$B$4)-MONTH(D25))/F25)+1)))) | I25: =IF($A25="","",IF(H25="","Not recorded",IF(H25<Methodology!$B$4,"Expired",IF(H25-Methodology!$B$4<=90,"Expiring within 90 days","Valid")))) | J25: =IF(OR($A25="",Vendor_Register!Y12=""),"",Vendor_Register!Y12) | K25: =IF(J25="","",J25-IF(C25="Critical",180,IF(C25="High",180,IF(C25="Medium",120,90)))) | L25: =IF($A25="","",IF(E25="","Not yet assessed",IF(E25<Methodology!$B$4,"Reassessment overdue",IF(I25="Expired","Attestation expired",IF(OR(I25="Expiring within 90 days",E25-Methodology!$B$4<=90),"Action due within 90 days","On track")))))
A26: =IF(Vendor_Register!A13="","",Vendor_Register!A13) | B26: =IF($A26="","",Vendor_Register!B13) | C26: =IF($A26="","",Vendor_Register!M13) | D26: =IF(OR($A26="",Vendor_Register!U13=""),"",Vendor_Register!U13) | E26: =IF($A26="","",Vendor_Register!W13) | F26: =IF($A26="","",INDEX(Methodology!$E$20:$E$23,MATCH(C26,Methodology!$A$20:$A$23,0))) | G26: =IF(OR($A26="",D26=""),"",IF(F26=0,"At renewal",EDATE(D26,F26*(INT(((YEAR(Methodology!$B$4)-YEAR(D26))*12+MONTH(Methodology!$B$4)-MONTH(D26))/F26)+1)))) | I26: =IF($A26="","",IF(H26="","Not recorded",IF(H26<Methodology!$B$4,"Expired",IF(H26-Methodology!$B$4<=90,"Expiring within 90 days","Valid")))) | J26: =IF(OR($A26="",Vendor_Register!Y13=""),"",Vendor_Register!Y13) | K26: =IF(J26="","",J26-IF(C26="Critical",180,IF(C26="High",180,IF(C26="Medium",120,90)))) | L26: =IF($A26="","",IF(E26="","Not yet assessed",IF(E26<Methodology!$B$4,"Reassessment overdue",IF(I26="Expired","Attestation expired",IF(OR(I26="Expiring within 90 days",E26-Methodology!$B$4<=90),"Action due within 90 days","On track")))))
A27: =IF(Vendor_Register!A14="","",Vendor_Register!A14) | B27: =IF($A27="","",Vendor_Register!B14) | C27: =IF($A27="","",Vendor_Register!M14) | D27: =IF(OR($A27="",Vendor_Register!U14=""),"",Vendor_Register!U14) | E27: =IF($A27="","",Vendor_Register!W14) | F27: =IF($A27="","",INDEX(Methodology!$E$20:$E$23,MATCH(C27,Methodology!$A$20:$A$23,0))) | G27: =IF(OR($A27="",D27=""),"",IF(F27=0,"At renewal",EDATE(D27,F27*(INT(((YEAR(Methodology!$B$4)-YEAR(D27))*12+MONTH(Methodology!$B$4)-MONTH(D27))/F27)+1)))) | I27: =IF($A27="","",IF(H27="","Not recorded",IF(H27<Methodology!$B$4,"Expired",IF(H27-Methodology!$B$4<=90,"Expiring within 90 days","Valid")))) | J27: =IF(OR($A27="",Vendor_Register!Y14=""),"",Vendor_Register!Y14) | K27: =IF(J27="","",J27-IF(C27="Critical",180,IF(C27="High",180,IF(C27="Medium",120,90)))) | L27: =IF($A27="","",IF(E27="","Not yet assessed",IF(E27<Methodology!$B$4,"Reassessment overdue",IF(I27="Expired","Attestation expired",IF(OR(I27="Expiring within 90 days",E27-Methodology!$B$4<=90),"Action due within 90 days","On track")))))
A28: =IF(Vendor_Register!A15="","",Vendor_Register!A15) | B28: =IF($A28="","",Vendor_Register!B15) | C28: =IF($A28="","",Vendor_Register!M15) | D28: =IF(OR($A28="",Vendor_Register!U15=""),"",Vendor_Register!U15) | E28: =IF($A28="","",Vendor_Register!W15) | F28: =IF($A28="","",INDEX(Methodology!$E$20:$E$23,MATCH(C28,Methodology!$A$20:$A$23,0))) | G28: =IF(OR($A28="",D28=""),"",IF(F28=0,"At renewal",EDATE(D28,F28*(INT(((YEAR(Methodology!$B$4)-YEAR(D28))*12+MONTH(Methodology!$B$4)-MONTH(D28))/F28)+1)))) | I28: =IF($A28="","",IF(H28="","Not recorded",IF(H28<Methodology!$B$4,"Expired",IF(H28-Methodology!$B$4<=90,"Expiring within 90 days","Valid")))) | J28: =IF(OR($A28="",Vendor_Register!Y15=""),"",Vendor_Register!Y15) | K28: =IF(J28="","",J28-IF(C28="Critical",180,IF(C28="High",180,IF(C28="Medium",120,90)))) | L28: =IF($A28="","",IF(E28="","Not yet assessed",IF(E28<Methodology!$B$4,"Reassessment overdue",IF(I28="Expired","Attestation expired",IF(OR(I28="Expiring within 90 days",E28-Methodology!$B$4<=90),"Action due within 90 days","On track")))))
A30: C. Event-driven reassessment triggers (reassess regardless of schedule)
A31: 1. Security incident or data breach at the vendor or one of its subprocessors.
A32: 2. Material change in service scope, hosting location, ownership or subprocessors.
A33: 3. Lapse, qualification or adverse opinion in a SOC 2 or ISO certification.
A34: 4. Significant change to data types shared with the vendor or to the vendor's access to our systems.
A35: 5. Major AI model change, new AI feature, or change to the vendor's data-use or retention terms.
A36: 6. New or changed regulation affecting the service (e.g., EU AI Act obligations coming into force).
A37: 7. Repeated SLA breaches, financial distress, or negative adverse-media findings.
